[{"Viscosity":14.7,"Wt":20,"Time":35.6},{"Viscosity":27.5,"Wt":20,"Time":54.3},{"Viscosity":42.0,"Wt":20,"Time":75.6},{"Viscosity":75.7,"Wt":20,"Time":121.2},{"Viscosity":89.7,"Wt":20,"Time":150.8},{"Viscosity":146.6,"Wt":20,"Time":229.0},{"Viscosity":158.3,"Wt":20,"Time":270.0},{"Viscosity":14.7,"Wt":50,"Time":17.6},{"Viscosity":27.5,"Wt":50,"Time":24.3},{"Viscosity":42.0,"Wt":50,"Time":31.4},{"Viscosity":75.7,"Wt":50,"Time":47.2},{"Viscosity":89.7,"Wt":50,"Time":58.3},{"Viscosity":146.6,"Wt":50,"Time":85.6},{"Viscosity":158.3,"Wt":50,"Time":101.1},{"Viscosity":161.1,"Wt":50,"Time":92.2},{"Viscosity":298.3,"Wt":50,"Time":187.2},{"Viscosity":75.7,"Wt":100,"Time":24.6},{"Viscosity":89.7,"Wt":100,"Time":30.0},{"Viscosity":146.6,"Wt":100,"Time":41.7},{"Viscosity":158.3,"Wt":100,"Time":50.3},{"Viscosity":161.1,"Wt":100,"Time":45.1},{"Viscosity":298.3,"Wt":100,"Time":89.0},{"Viscosity":298.3,"Wt":100,"Time":86.5}]