[{"class":"1st class","age":"adults","sex":"man","survived":"yes"},{"class":"1st class","age":"adults","sex":"man","survived":"yes"},{"class":"1st class","age":"adults","sex":"man","survived":"yes"},{"class":"1st class","age":"adults","sex":"man","survived":"yes"},{"class":"1st class","age":"adults","sex":"man","survived":"yes"},{"class":"1st class","age":"adults","sex":"man","survived":"yes"},{"class":"1st class","age":"adults","sex":"man","survived":"yes"},{"class":"1st class","age":"adults","sex":"man","survived":"yes"},{"class":"1st class","age":"adults","sex":"man","survived":"yes"},{"class":"1st class","age":"adults","sex":"man","survived":"yes"},{"class":"1st class","age":"adults","sex":"man","survived":"yes"},{"class":"1st class","age":"adults","sex":"man","survived":"yes"},{"class":"1st class","age":"adults","sex":"man","survived":"yes"},{"class":"1st class","age":"adults","sex":"man","survived":"yes"},{"class":"1st class","age":"adults","sex":"man","survived":"yes"},{"class":"1st class","age":"adults","sex":"man","survived":"yes"},{"class":"1st class","age":"adults","sex":"man","survived":"yes"},{"class":"1st class","age":"adults","sex":"man","survived":"yes"},{"class":"1st class","age":"adults","sex":"man","survived":"yes"},{"class":"1st class","age":"adults","sex":"man","survived":"yes"},{"class":"1st class","age":"adults","sex":"man","survived":"yes"},{"class":"1st class","age":"adults","sex":"man","survived":"yes"},{"class":"1st class","age":"adults","sex":"man","survived":"yes"},{"class":"1st class","age":"adults","sex":"man","survived":"yes"},{"class":"1st class","age":"adults","sex":"man","survived":"yes"},{"class":"1st class","age":"adults","sex":"man","survived":"yes"},{"class":"1st class","age":"adults","sex":"man","survived":"yes"},{"class":"1st class","age":"adults","sex":"man","survived":"yes"},{"class":"1st class","age":"adults","sex":"man","survived":"yes"},{"class":"1st class","age":"adults","sex":"man","survived":"yes"},{"class":"1st class","age":"adults","sex":"man","survived":"yes"},{"class":"1st class","age":"adults","sex":"man","survived":"yes"},{"class":"1st class","age":"adults","sex":"man","survived":"yes"},{"class":"1st class","age":"adults","sex":"man","survived":"yes"},{"class":"1st class","age":"adults","sex":"man","survived":"yes"},{"class":"1st class","age":"adults","sex":"man","survived":"yes"},{"class":"1st class","age":"adults","sex":"man","survived":"yes"},{"class":"1st class","age":"adults","sex":"man","survived":"yes"},{"class":"1st class","age":"adults","sex":"man","survived":"yes"},{"class":"1st class","age":"adults","sex":"man","survived":"yes"},{"class":"1st class","age":"adults","sex":"man","survived":"yes"},{"class":"1st class","age":"adults","sex":"man","survived":"yes"},{"class":"1st class","age":"adults","sex":"man","survived":"yes"},{"class":"1st class","age":"adults","sex":"man","survived":"yes"},{"class":"1st class","age":"adults","sex":"man","survived":"yes"},{"class":"1st class","age":"adults","sex":"man","survived":"yes"},{"class":"1st class","age":"adults","sex":"man","survived":"yes"},{"class":"1st class","age":"adults","sex":"man","survived":"yes"},{"class":"1st class","age":"adults","sex":"man","survived":"yes"},{"class":"1st class","age":"adults","sex":"man","survived":"yes"},{"class":"1st class","age":"adults","sex":"man","survived":"yes"},{"class":"1st class","age":"adults","sex":"man","survived":"yes"},{"class":"1st class","age":"adults","sex":"man","survived":"yes"},{"class":"1st class","age":"adults","sex":"man","survived":"yes"},{"class":"1st class","age":"adults","sex":"man","survived":"yes"},{"class":"1st class","age":"adults","sex":"man","survived":"yes"},{"class":"1st class","age":"adults","sex":"man","survived":"yes"},{"class":"1st class","age":"adults","sex":"man","survived":"no"},{"class":"1st class","age":"adults","sex":"man","survived":"no"},{"class":"1st class","age":"adults","sex":"man","survived":"no"},{"class":"1st class","age":"adults","sex":"man","survived":"no"},{"class":"1st class","age":"adults","sex":"man","survived":"no"},{"class":"1st class","age":"adults","sex":"man","survived":"no"},{"class":"1st class","age":"adults","sex":"man","survived":"no"},{"class":"1st class","age":"adults","sex":"man","survived":"no"},{"class":"1st class","age":"adults","sex":"man","survived":"no"},{"class":"1st class","age":"adults","sex":"man","survived":"no"},{"class":"1st class","age":"adults","sex":"man","survived":"no"},{"class":"1st class","age":"adults","sex":"man","survived":"no"},{"class":"1st class","age":"adults","sex":"man","survived":"no"},{"class":"1st class","age":"adults","sex":"man","survived":"no"},{"class":"1st class","age":"adults","sex":"man","survived":"no"},{"class":"1st class","age":"adults","sex":"man","survived":"no"},{"class":"1st class","age":"adults","sex":"man","survived":"no"},{"class":"1st class","age":"adults","sex":"man","survived":"no"},{"class":"1st class","age":"adults","sex":"man","survived":"no"},{"class":"1st class","age":"adults","sex":"man","survived":"no"},{"class":"1st class","age":"adults","sex":"man","survived":"no"},{"class":"1st class","age":"adults","sex":"man","survived":"no"},{"class":"1st class","age":"adults","sex":"man","survived":"no"},{"class":"1st class","age":"adults","sex":"man","survived":"no"},{"class":"1st class","age":"adults","sex":"man","survived":"no"},{"class":"1st class","age":"adults","sex":"man","survived":"no"},{"class":"1st class","age":"adults","sex":"man","survived":"no"},{"class":"1st class","age":"adults","sex":"man","survived":"no"},{"class":"1st class","age":"adults","sex":"man","survived":"no"},{"class":"1st class","age":"adults","sex":"man","survived":"no"},{"class":"1st class","age":"adults","sex":"man","survived":"no"},{"class":"1st class","age":"adults","sex":"man","survived":"no"},{"class":"1st class","age":"adults","sex":"man","survived":"no"},{"class":"1st class","age":"adults","sex":"man","survived":"no"},{"class":"1st class","age":"adults","sex":"man","survived":"no"},{"class":"1st class","age":"adults","sex":"man","survived":"no"},{"class":"1st class","age":"adults","sex":"man","survived":"no"},{"class":"1st class","age":"adults","sex":"man","survived":"no"},{"class":"1st class","age":"adults","sex":"man","survived":"no"},{"class":"1st class","age":"adults","sex":"man","survived":"no"},{"class":"1st class","age":"adults","sex":"man","survived":"no"},{"class":"1st class","age":"adults","sex":"man","survived":"no"},{"class":"1st class","age":"adults","sex":"man","survived":"no"},{"class":"1st class","age":"adults","sex":"man","survived":"no"},{"class":"1st class","age":"adults","sex":"man","survived":"no"},{"class":"1st class","age":"adults","sex":"man","survived":"no"},{"class":"1st class","age":"adults","sex":"man","survived":"no"},{"class":"1st class","age":"adults","sex":"man","survived":"no"},{"class":"1st class","age":"adults","sex":"man","survived":"no"},{"class":"1st class","age":"adults","sex":"man","survived":"no"},{"class":"1st class","age":"adults","sex":"man","survived":"no"},{"class":"1st class","age":"adults","sex":"man","survived":"no"},{"class":"1st class","age":"adults","sex":"man","survived":"no"},{"class":"1st class","age":"adults","sex":"man","survived":"no"},{"class":"1st class","age":"adults","sex":"man","survived":"no"},{"class":"1st class","age":"adults","sex":"man","survived":"no"},{"class":"1st class","age":"adults","sex":"man","survived":"no"},{"class":"1st class","age":"adults","sex":"man","survived":"no"},{"class":"1st class","age":"adults","sex":"man","survived":"no"},{"class":"1st class","age":"adults","sex":"man","survived":"no"},{"class":"1st class","age":"adults","sex":"man","survived":"no"},{"class":"1st class","age":"adults","sex":"man","survived":"no"},{"class":"1st class","age":"adults","sex":"man","survived":"no"},{"class":"1st class","age":"adults","sex":"man","survived":"no"},{"class":"1st class","age":"adults","sex":"man","survived":"no"},{"class":"1st class","age":"adults","sex":"man","survived":"no"},{"class":"1st class","age":"adults","sex":"man","survived":"no"},{"class":"1st class","age":"adults","sex":"man","survived":"no"},{"class":"1st class","age":"adults","sex":"man","survived":"no"},{"class":"1st class","age":"adults","sex":"man","survived":"no"},{"class":"1st class","age":"adults","sex":"man","survived":"no"},{"class":"1st class","age":"adults","sex":"man","survived":"no"},{"class":"1st class","age":"adults","sex":"man","survived":"no"},{"class":"1st class","age":"adults","sex":"man","survived":"no"},{"class":"1st class","age":"adults","sex":"man","survived":"no"},{"class":"1st class","age":"adults","sex":"man","survived":"no"},{"class":"1st class","age":"adults","sex":"man","survived":"no"},{"class":"1st class","age":"adults","sex":"man","survived":"no"},{"class":"1st class","age":"adults","sex":"man","survived":"no"},{"class":"1st class","age":"adults","sex":"man","survived":"no"},{"class":"1st class","age":"adults","sex":"man","survived":"no"},{"class":"1st class","age":"adults","sex":"man","survived":"no"},{"class":"1st class","age":"adults","sex":"man","survived":"no"},{"class":"1st class","age":"adults","sex":"man","survived":"no"},{"class":"1st class","age":"adults","sex":"man","survived":"no"},{"class":"1st class","age":"adults","sex":"man","survived":"no"},{"class":"1st class","age":"adults","sex":"man","survived":"no"},{"class":"1st class","age":"adults","sex":"man","survived":"no"},{"class":"1st class","age":"adults","sex":"man","survived":"no"},{"class":"1st class","age":"adults","sex":"man","survived":"no"},{"class":"1st class","age":"adults","sex":"man","survived":"no"},{"class":"1st class","age":"adults","sex":"man","survived":"no"},{"class":"1st class","age":"adults","sex":"man","survived":"no"},{"class":"1st class","age":"adults","sex":"man","survived":"no"},{"class":"1st class","age":"adults","sex":"man","survived":"no"},{"class":"1st class","age":"adults","sex":"man","survived":"no"},{"class":"1st class","age":"adults","sex":"man","survived":"no"},{"class":"1st class","age":"adults","sex":"man","survived":"no"},{"class":"1st class","age":"adults","sex":"man","survived":"no"},{"class":"1st class","age":"adults","sex":"man","survived":"no"},{"class":"1st class","age":"adults","sex":"man","survived":"no"},{"class":"1st class","age":"adults","sex":"man","survived":"no"},{"class":"1st class","age":"adults","sex":"man","survived":"no"},{"class":"1st class","age":"adults","sex":"man","survived":"no"},{"class":"1st class","age":"adults","sex":"man","survived":"no"},{"class":"1st class","age":"adults","sex":"man","survived":"no"},{"class":"1st class","age":"adults","sex":"man","survived":"no"},{"class":"1st class","age":"adults","sex":"man","survived":"no"},{"class":"1st class","age":"adults","sex":"man","survived":"no"},{"class":"1st class","age":"adults","sex":"man","survived":"no"},{"class":"1st class","age":"adults","sex":"man","survived":"no"},{"class":"1st class","age":"adults","sex":"man","survived":"no"},{"class":"1st class","age":"adults","sex":"man","survived":"no"},{"class":"1st class","age":"adults","sex":"man","survived":"no"},{"class":"1st class","age":"adults","sex":"man","survived":"no"},{"class":"1st class","age":"adults","sex":"man","survived":"no"},{"class":"1st class","age":"adults","sex":"man","survived":"no"},{"class":"1st class","age":"adults","sex":"man","survived":"no"},{"class":"1st class","age":"adults","sex":"women","survived":"yes"},{"class":"1st class","age":"adults","sex":"women","survived":"yes"},{"class":"1st class","age":"adults","sex":"women","survived":"yes"},{"class":"1st class","age":"adults","sex":"women","survived":"yes"},{"class":"1st class","age":"adults","sex":"women","survived":"yes"},{"class":"1st class","age":"adults","sex":"women","survived":"yes"},{"class":"1st class","age":"adults","sex":"women","survived":"yes"},{"class":"1st class","age":"adults","sex":"women","survived":"yes"},{"class":"1st class","age":"adults","sex":"women","survived":"yes"},{"class":"1st class","age":"adults","sex":"women","survived":"yes"},{"class":"1st class","age":"adults","sex":"women","survived":"yes"},{"class":"1st class","age":"adults","sex":"women","survived":"yes"},{"class":"1st class","age":"adults","sex":"women","survived":"yes"},{"class":"1st class","age":"adults","sex":"women","survived":"yes"},{"class":"1st class","age":"adults","sex":"women","survived":"yes"},{"class":"1st class","age":"adults","sex":"women","survived":"yes"},{"class":"1st class","age":"adults","sex":"women","survived":"yes"},{"class":"1st class","age":"adults","sex":"women","survived":"yes"},{"class":"1st class","age":"adults","sex":"women","survived":"yes"},{"class":"1st class","age":"adults","sex":"women","survived":"yes"},{"class":"1st class","age":"adults","sex":"women","survived":"yes"},{"class":"1st class","age":"adults","sex":"women","survived":"yes"},{"class":"1st class","age":"adults","sex":"women","survived":"yes"},{"class":"1st class","age":"adults","sex":"women","survived":"yes"},{"class":"1st class","age":"adults","sex":"women","survived":"yes"},{"class":"1st class","age":"adults","sex":"women","survived":"yes"},{"class":"1st class","age":"adults","sex":"women","survived":"yes"},{"class":"1st class","age":"adults","sex":"women","survived":"yes"},{"class":"1st class","age":"adults","sex":"women","survived":"yes"},{"class":"1st class","age":"adults","sex":"women","survived":"yes"},{"class":"1st class","age":"adults","sex":"women","survived":"yes"},{"class":"1st class","age":"adults","sex":"women","survived":"yes"},{"class":"1st class","age":"adults","sex":"women","survived":"yes"},{"class":"1st class","age":"adults","sex":"women","survived":"yes"},{"class":"1st class","age":"adults","sex":"women","survived":"yes"},{"class":"1st class","age":"adults","sex":"women","survived":"yes"},{"class":"1st class","age":"adults","sex":"women","survived":"yes"},{"class":"1st class","age":"adults","sex":"women","survived":"yes"},{"class":"1st class","age":"adults","sex":"women","survived":"yes"},{"class":"1st class","age":"adults","sex":"women","survived":"yes"},{"class":"1st class","age":"adults","sex":"women","survived":"yes"},{"class":"1st class","age":"adults","sex":"women","survived":"yes"},{"class":"1st class","age":"adults","sex":"women","survived":"yes"},{"class":"1st class","age":"adults","sex":"women","survived":"yes"},{"class":"1st class","age":"adults","sex":"women","survived":"yes"},{"class":"1st class","age":"adults","sex":"women","survived":"yes"},{"class":"1st class","age":"adults","sex":"women","survived":"yes"},{"class":"1st class","age":"adults","sex":"women","survived":"yes"},{"class":"1st class","age":"adults","sex":"women","survived":"yes"},{"class":"1st class","age":"adults","sex":"women","survived":"yes"},{"class":"1st class","age":"adults","sex":"women","survived":"yes"},{"class":"1st class","age":"adults","sex":"women","survived":"yes"},{"class":"1st class","age":"adults","sex":"women","survived":"yes"},{"class":"1st class","age":"adults","sex":"women","survived":"yes"},{"class":"1st class","age":"adults","sex":"women","survived":"yes"},{"class":"1st class","age":"adults","sex":"women","survived":"yes"},{"class":"1st class","age":"adults","sex":"women","survived":"yes"},{"class":"1st class","age":"adults","sex":"women","survived":"yes"},{"class":"1st class","age":"adults","sex":"women","survived":"yes"},{"class":"1st class","age":"adults","sex":"women","survived":"yes"},{"class":"1st class","age":"adults","sex":"women","survived":"yes"},{"class":"1st class","age":"adults","sex":"women","survived":"yes"},{"class":"1st class","age":"adults","sex":"women","survived":"yes"},{"class":"1st class","age":"adults","sex":"women","survived":"yes"},{"class":"1st class","age":"adults","sex":"women","survived":"yes"},{"class":"1st class","age":"adults","sex":"women","survived":"yes"},{"class":"1st class","age":"adults","sex":"women","survived":"yes"},{"class":"1st class","age":"adults","sex":"women","survived":"yes"},{"class":"1st class","age":"adults","sex":"women","survived":"yes"},{"class":"1st class","age":"adults","sex":"women","survived":"yes"},{"class":"1st class","age":"adults","sex":"women","survived":"yes"},{"class":"1st class","age":"adults","sex":"women","survived":"yes"},{"class":"1st class","age":"adults","sex":"women","survived":"yes"},{"class":"1st class","age":"adults","sex":"women","survived":"yes"},{"class":"1st class","age":"adults","sex":"women","survived":"yes"},{"class":"1st class","age":"adults","sex":"women","survived":"yes"},{"class":"1st class","age":"adults","sex":"women","survived":"yes"},{"class":"1st class","age":"adults","sex":"women","survived":"yes"},{"class":"1st class","age":"adults","sex":"women","survived":"yes"},{"class":"1st class","age":"adults","sex":"women","survived":"yes"},{"class":"1st class","age":"adults","sex":"women","survived":"yes"},{"class":"1st class","age":"adults","sex":"women","survived":"yes"},{"class":"1st class","age":"adults","sex":"women","survived":"yes"},{"class":"1st class","age":"adults","sex":"women","survived":"yes"},{"class":"1st class","age":"adults","sex":"women","survived":"yes"},{"class":"1st class","age":"adults","sex":"women","survived":"yes"},{"class":"1st class","age":"adults","sex":"women","survived":"yes"},{"class":"1st class","age":"adults","sex":"women","survived":"yes"},{"class":"1st class","age":"adults","sex":"women","survived":"yes"},{"class":"1st class","age":"adults","sex":"women","survived":"yes"},{"class":"1st class","age":"adults","sex":"women","survived":"yes"},{"class":"1st class","age":"adults","sex":"women","survived":"yes"},{"class":"1st class","age":"adults","sex":"women","survived":"yes"},{"class":"1st class","age":"adults","sex":"women","survived":"yes"},{"class":"1st class","age":"adults","sex":"women","survived":"yes"},{"class":"1st class","age":"adults","sex":"women","survived":"yes"},{"class":"1st class","age":"adults","sex":"women","survived":"yes"},{"class":"1st class","age":"adults","sex":"women","survived":"yes"},{"class":"1st class","age":"adults","sex":"women","survived":"yes"},{"class":"1st class","age":"adults","sex":"women","survived":"yes"},{"class":"1st class","age":"adults","sex":"women","survived":"yes"},{"class":"1st class","age":"adults","sex":"women","survived":"yes"},{"class":"1st class","age":"adults","sex":"women","survived":"yes"},{"class":"1st class","age":"adults","sex":"women","survived":"yes"},{"class":"1st class","age":"adults","sex":"women","survived":"yes"},{"class":"1st class","age":"adults","sex":"women","survived":"yes"},{"class":"1st class","age":"adults","sex":"women","survived":"yes"},{"class":"1st class","age":"adults","sex":"women","survived":"yes"},{"class":"1st class","age":"adults","sex":"women","survived":"yes"},{"class":"1st class","age":"adults","sex":"women","survived":"yes"},{"class":"1st class","age":"adults","sex":"women","survived":"yes"},{"class":"1st class","age":"adults","sex":"women","survived":"yes"},{"class":"1st class","age":"adults","sex":"women","survived":"yes"},{"class":"1st class","age":"adults","sex":"women","survived":"yes"},{"class":"1st class","age":"adults","sex":"women","survived":"yes"},{"class":"1st class","age":"adults","sex":"women","survived":"yes"},{"class":"1st class","age":"adults","sex":"women","survived":"yes"},{"class":"1st class","age":"adults","sex":"women","survived":"yes"},{"class":"1st class","age":"adults","sex":"women","survived":"yes"},{"class":"1st class","age":"adults","sex":"women","survived":"yes"},{"class":"1st class","age":"adults","sex":"women","survived":"yes"},{"class":"1st class","age":"adults","sex":"women","survived":"yes"},{"class":"1st class","age":"adults","sex":"women","survived":"yes"},{"class":"1st class","age":"adults","sex":"women","survived":"yes"},{"class":"1st class","age":"adults","sex":"women","survived":"yes"},{"class":"1st class","age":"adults","sex":"women","survived":"yes"},{"class":"1st class","age":"adults","sex":"women","survived":"yes"},{"class":"1st class","age":"adults","sex":"women","survived":"yes"},{"class":"1st class","age":"adults","sex":"women","survived":"yes"},{"class":"1st class","age":"adults","sex":"women","survived":"yes"},{"class":"1st class","age":"adults","sex":"women","survived":"yes"},{"class":"1st class","age":"adults","sex":"women","survived":"yes"},{"class":"1st class","age":"adults","sex":"women","survived":"yes"},{"class":"1st class","age":"adults","sex":"women","survived":"yes"},{"class":"1st class","age":"adults","sex":"women","survived":"yes"},{"class":"1st class","age":"adults","sex":"women","survived":"yes"},{"class":"1st class","age":"adults","sex":"women","survived":"yes"},{"class":"1st class","age":"adults","sex":"women","survived":"yes"},{"class":"1st class","age":"adults","sex":"women","survived":"yes"},{"class":"1st class","age":"adults","sex":"women","survived":"yes"},{"class":"1st class","age":"adults","sex":"women","survived":"no"},{"class":"1st class","age":"adults","sex":"women","survived":"no"},{"class":"1st class","age":"adults","sex":"women","survived":"no"},{"class":"1st class","age":"adults","sex":"women","survived":"no"},{"class":"1st class","age":"child","sex":"man","survived":"yes"},{"class":"1st class","age":"child","sex":"man","survived":"yes"},{"class":"1st class","age":"child","sex":"man","survived":"yes"},{"class":"1st class","age":"child","sex":"man","survived":"yes"},{"class":"1st class","age":"child","sex":"man","survived":"yes"},{"class":"1st class","age":"child","sex":"women","survived":"yes"},{"class":"2nd class","age":"adults","sex":"man","survived":"yes"},{"class":"2nd class","age":"adults","sex":"man","survived":"yes"},{"class":"2nd class","age":"adults","sex":"man","survived":"yes"},{"class":"2nd class","age":"adults","sex":"man","survived":"yes"},{"class":"2nd class","age":"adults","sex":"man","survived":"yes"},{"class":"2nd class","age":"adults","sex":"man","survived":"yes"},{"class":"2nd class","age":"adults","sex":"man","survived":"yes"},{"class":"2nd class","age":"adults","sex":"man","survived":"yes"},{"class":"2nd class","age":"adults","sex":"man","survived":"yes"},{"class":"2nd class","age":"adults","sex":"man","survived":"yes"},{"class":"2nd class","age":"adults","sex":"man","survived":"yes"},{"class":"2nd class","age":"adults","sex":"man","survived":"yes"},{"class":"2nd class","age":"adults","sex":"man","survived":"yes"},{"class":"2nd class","age":"adults","sex":"man","survived":"yes"},{"class":"2nd class","age":"adults","sex":"man","survived":"no"},{"class":"2nd class","age":"adults","sex":"man","survived":"no"},{"class":"2nd class","age":"adults","sex":"man","survived":"no"},{"class":"2nd class","age":"adults","sex":"man","survived":"no"},{"class":"2nd class","age":"adults","sex":"man","survived":"no"},{"class":"2nd class","age":"adults","sex":"man","survived":"no"},{"class":"2nd class","age":"adults","sex":"man","survived":"no"},{"class":"2nd class","age":"adults","sex":"man","survived":"no"},{"class":"2nd class","age":"adults","sex":"man","survived":"no"},{"class":"2nd class","age":"adults","sex":"man","survived":"no"},{"class":"2nd class","age":"adults","sex":"man","survived":"no"},{"class":"2nd class","age":"adults","sex":"man","survived":"no"},{"class":"2nd class","age":"adults","sex":"man","survived":"no"},{"class":"2nd class","age":"adults","sex":"man","survived":"no"},{"class":"2nd class","age":"adults","sex":"man","survived":"no"},{"class":"2nd class","age":"adults","sex":"man","survived":"no"},{"class":"2nd class","age":"adults","sex":"man","survived":"no"},{"class":"2nd class","age":"adults","sex":"man","survived":"no"},{"class":"2nd class","age":"adults","sex":"man","survived":"no"},{"class":"2nd class","age":"adults","sex":"man","survived":"no"},{"class":"2nd class","age":"adults","sex":"man","survived":"no"},{"class":"2nd class","age":"adults","sex":"man","survived":"no"},{"class":"2nd class","age":"adults","sex":"man","survived":"no"},{"class":"2nd class","age":"adults","sex":"man","survived":"no"},{"class":"2nd class","age":"adults","sex":"man","survived":"no"},{"class":"2nd class","age":"adults","sex":"man","survived":"no"},{"class":"2nd class","age":"adults","sex":"man","survived":"no"},{"class":"2nd class","age":"adults","sex":"man","survived":"no"},{"class":"2nd class","age":"adults","sex":"man","survived":"no"},{"class":"2nd class","age":"adults","sex":"man","survived":"no"},{"class":"2nd class","age":"adults","sex":"man","survived":"no"},{"class":"2nd class","age":"adults","sex":"man","survived":"no"},{"class":"2nd class","age":"adults","sex":"man","survived":"no"},{"class":"2nd class","age":"adults","sex":"man","survived":"no"},{"class":"2nd class","age":"adults","sex":"man","survived":"no"},{"class":"2nd class","age":"adults","sex":"man","survived":"no"},{"class":"2nd class","age":"adults","sex":"man","survived":"no"},{"class":"2nd class","age":"adults","sex":"man","survived":"no"},{"class":"2nd class","age":"adults","sex":"man","survived":"no"},{"class":"2nd class","age":"adults","sex":"man","survived":"no"},{"class":"2nd class","age":"adults","sex":"man","survived":"no"},{"class":"2nd class","age":"adults","sex":"man","survived":"no"},{"class":"2nd class","age":"adults","sex":"man","survived":"no"},{"class":"2nd class","age":"adults","sex":"man","survived":"no"},{"class":"2nd class","age":"adults","sex":"man","survived":"no"},{"class":"2nd class","age":"adults","sex":"man","survived":"no"},{"class":"2nd class","age":"adults","sex":"man","survived":"no"},{"class":"2nd class","age":"adults","sex":"man","survived":"no"},{"class":"2nd class","age":"adults","sex":"man","survived":"no"},{"class":"2nd class","age":"adults","sex":"man","survived":"no"},{"class":"2nd class","age":"adults","sex":"man","survived":"no"},{"class":"2nd class","age":"adults","sex":"man","survived":"no"},{"class":"2nd class","age":"adults","sex":"man","survived":"no"},{"class":"2nd class","age":"adults","sex":"man","survived":"no"},{"class":"2nd class","age":"adults","sex":"man","survived":"no"},{"class":"2nd class","age":"adults","sex":"man","survived":"no"},{"class":"2nd class","age":"adults","sex":"man","survived":"no"},{"class":"2nd class","age":"adults","sex":"man","survived":"no"},{"class":"2nd class","age":"adults","sex":"man","survived":"no"},{"class":"2nd class","age":"adults","sex":"man","survived":"no"},{"class":"2nd class","age":"adults","sex":"man","survived":"no"},{"class":"2nd class","age":"adults","sex":"man","survived":"no"},{"class":"2nd class","age":"adults","sex":"man","survived":"no"},{"class":"2nd class","age":"adults","sex":"man","survived":"no"},{"class":"2nd class","age":"adults","sex":"man","survived":"no"},{"class":"2nd class","age":"adults","sex":"man","survived":"no"},{"class":"2nd class","age":"adults","sex":"man","survived":"no"},{"class":"2nd class","age":"adults","sex":"man","survived":"no"},{"class":"2nd class","age":"adults","sex":"man","survived":"no"},{"class":"2nd class","age":"adults","sex":"man","survived":"no"},{"class":"2nd class","age":"adults","sex":"man","survived":"no"},{"class":"2nd class","age":"adults","sex":"man","survived":"no"},{"class":"2nd class","age":"adults","sex":"man","survived":"no"},{"class":"2nd class","age":"adults","sex":"man","survived":"no"},{"class":"2nd class","age":"adults","sex":"man","survived":"no"},{"class":"2nd class","age":"adults","sex":"man","survived":"no"},{"class":"2nd class","age":"adults","sex":"man","survived":"no"},{"class":"2nd class","age":"adults","sex":"man","survived":"no"},{"class":"2nd class","age":"adults","sex":"man","survived":"no"},{"class":"2nd class","age":"adults","sex":"man","survived":"no"},{"class":"2nd class","age":"adults","sex":"man","survived":"no"},{"class":"2nd class","age":"adults","sex":"man","survived":"no"},{"class":"2nd class","age":"adults","sex":"man","survived":"no"},{"class":"2nd class","age":"adults","sex":"man","survived":"no"},{"class":"2nd class","age":"adults","sex":"man","survived":"no"},{"class":"2nd class","age":"adults","sex":"man","survived":"no"},{"class":"2nd class","age":"adults","sex":"man","survived":"no"},{"class":"2nd class","age":"adults","sex":"man","survived":"no"},{"class":"2nd class","age":"adults","sex":"man","survived":"no"},{"class":"2nd class","age":"adults","sex":"man","survived":"no"},{"class":"2nd class","age":"adults","sex":"man","survived":"no"},{"class":"2nd class","age":"adults","sex":"man","survived":"no"},{"class":"2nd class","age":"adults","sex":"man","survived":"no"},{"class":"2nd class","age":"adults","sex":"man","survived":"no"},{"class":"2nd class","age":"adults","sex":"man","survived":"no"},{"class":"2nd class","age":"adults","sex":"man","survived":"no"},{"class":"2nd class","age":"adults","sex":"man","survived":"no"},{"class":"2nd class","age":"adults","sex":"man","survived":"no"},{"class":"2nd class","age":"adults","sex":"man","survived":"no"},{"class":"2nd class","age":"adults","sex":"man","survived":"no"},{"class":"2nd class","age":"adults","sex":"man","survived":"no"},{"class":"2nd class","age":"adults","sex":"man","survived":"no"},{"class":"2nd class","age":"adults","sex":"man","survived":"no"},{"class":"2nd class","age":"adults","sex":"man","survived":"no"},{"class":"2nd class","age":"adults","sex":"man","survived":"no"},{"class":"2nd class","age":"adults","sex":"man","survived":"no"},{"class":"2nd class","age":"adults","sex":"man","survived":"no"},{"class":"2nd class","age":"adults","sex":"man","survived":"no"},{"class":"2nd class","age":"adults","sex":"man","survived":"no"},{"class":"2nd class","age":"adults","sex":"man","survived":"no"},{"class":"2nd class","age":"adults","sex":"man","survived":"no"},{"class":"2nd class","age":"adults","sex":"man","survived":"no"},{"class":"2nd class","age":"adults","sex":"man","survived":"no"},{"class":"2nd class","age":"adults","sex":"man","survived":"no"},{"class":"2nd class","age":"adults","sex":"man","survived":"no"},{"class":"2nd class","age":"adults","sex":"man","survived":"no"},{"class":"2nd class","age":"adults","sex":"man","survived":"no"},{"class":"2nd class","age":"adults","sex":"man","survived":"no"},{"class":"2nd class","age":"adults","sex":"man","survived":"no"},{"class":"2nd class","age":"adults","sex":"man","survived":"no"},{"class":"2nd class","age":"adults","sex":"man","survived":"no"},{"class":"2nd class","age":"adults","sex":"man","survived":"no"},{"class":"2nd class","age":"adults","sex":"man","survived":"no"},{"class":"2nd class","age":"adults","sex":"man","survived":"no"},{"class":"2nd class","age":"adults","sex":"man","survived":"no"},{"class":"2nd class","age":"adults","sex":"man","survived":"no"},{"class":"2nd class","age":"adults","sex":"man","survived":"no"},{"class":"2nd class","age":"adults","sex":"man","survived":"no"},{"class":"2nd class","age":"adults","sex":"man","survived":"no"},{"class":"2nd class","age":"adults","sex":"man","survived":"no"},{"class":"2nd class","age":"adults","sex":"man","survived":"no"},{"class":"2nd class","age":"adults","sex":"man","survived":"no"},{"class":"2nd class","age":"adults","sex":"man","survived":"no"},{"class":"2nd class","age":"adults","sex":"man","survived":"no"},{"class":"2nd class","age":"adults","sex":"man","survived":"no"},{"class":"2nd class","age":"adults","sex":"man","survived":"no"},{"class":"2nd class","age":"adults","sex":"man","survived":"no"},{"class":"2nd class","age":"adults","sex":"man","survived":"no"},{"class":"2nd class","age":"adults","sex":"man","survived":"no"},{"class":"2nd class","age":"adults","sex":"man","survived":"no"},{"class":"2nd class","age":"adults","sex":"man","survived":"no"},{"class":"2nd class","age":"adults","sex":"man","survived":"no"},{"class":"2nd class","age":"adults","sex":"man","survived":"no"},{"class":"2nd class","age":"adults","sex":"man","survived":"no"},{"class":"2nd class","age":"adults","sex":"man","survived":"no"},{"class":"2nd class","age":"adults","sex":"man","survived":"no"},{"class":"2nd class","age":"adults","sex":"man","survived":"no"},{"class":"2nd class","age":"adults","sex":"man","survived":"no"},{"class":"2nd class","age":"adults","sex":"man","survived":"no"},{"class":"2nd class","age":"adults","sex":"man","survived":"no"},{"class":"2nd class","age":"adults","sex":"man","survived":"no"},{"class":"2nd class","age":"adults","sex":"man","survived":"no"},{"class":"2nd class","age":"adults","sex":"man","survived":"no"},{"class":"2nd class","age":"adults","sex":"man","survived":"no"},{"class":"2nd class","age":"adults","sex":"women","survived":"yes"},{"class":"2nd class","age":"adults","sex":"women","survived":"yes"},{"class":"2nd class","age":"adults","sex":"women","survived":"yes"},{"class":"2nd class","age":"adults","sex":"women","survived":"yes"},{"class":"2nd class","age":"adults","sex":"women","survived":"yes"},{"class":"2nd class","age":"adults","sex":"women","survived":"yes"},{"class":"2nd class","age":"adults","sex":"women","survived":"yes"},{"class":"2nd class","age":"adults","sex":"women","survived":"yes"},{"class":"2nd class","age":"adults","sex":"women","survived":"yes"},{"class":"2nd class","age":"adults","sex":"women","survived":"yes"},{"class":"2nd class","age":"adults","sex":"women","survived":"yes"},{"class":"2nd class","age":"adults","sex":"women","survived":"yes"},{"class":"2nd class","age":"adults","sex":"women","survived":"yes"},{"class":"2nd class","age":"adults","sex":"women","survived":"yes"},{"class":"2nd class","age":"adults","sex":"women","survived":"yes"},{"class":"2nd class","age":"adults","sex":"women","survived":"yes"},{"class":"2nd class","age":"adults","sex":"women","survived":"yes"},{"class":"2nd class","age":"adults","sex":"women","survived":"yes"},{"class":"2nd class","age":"adults","sex":"women","survived":"yes"},{"class":"2nd class","age":"adults","sex":"women","survived":"yes"},{"class":"2nd class","age":"adults","sex":"women","survived":"yes"},{"class":"2nd class","age":"adults","sex":"women","survived":"yes"},{"class":"2nd class","age":"adults","sex":"women","survived":"yes"},{"class":"2nd class","age":"adults","sex":"women","survived":"yes"},{"class":"2nd class","age":"adults","sex":"women","survived":"yes"},{"class":"2nd class","age":"adults","sex":"women","survived":"yes"},{"class":"2nd class","age":"adults","sex":"women","survived":"yes"},{"class":"2nd class","age":"adults","sex":"women","survived":"yes"},{"class":"2nd class","age":"adults","sex":"women","survived":"yes"},{"class":"2nd class","age":"adults","sex":"women","survived":"yes"},{"class":"2nd class","age":"adults","sex":"women","survived":"yes"},{"class":"2nd class","age":"adults","sex":"women","survived":"yes"},{"class":"2nd class","age":"adults","sex":"women","survived":"yes"},{"class":"2nd class","age":"adults","sex":"women","survived":"yes"},{"class":"2nd class","age":"adults","sex":"women","survived":"yes"},{"class":"2nd class","age":"adults","sex":"women","survived":"yes"},{"class":"2nd class","age":"adults","sex":"women","survived":"yes"},{"class":"2nd class","age":"adults","sex":"women","survived":"yes"},{"class":"2nd class","age":"adults","sex":"women","survived":"yes"},{"class":"2nd class","age":"adults","sex":"women","survived":"yes"},{"class":"2nd class","age":"adults","sex":"women","survived":"yes"},{"class":"2nd class","age":"adults","sex":"women","survived":"yes"},{"class":"2nd class","age":"adults","sex":"women","survived":"yes"},{"class":"2nd class","age":"adults","sex":"women","survived":"yes"},{"class":"2nd class","age":"adults","sex":"women","survived":"yes"},{"class":"2nd class","age":"adults","sex":"women","survived":"yes"},{"class":"2nd class","age":"adults","sex":"women","survived":"yes"},{"class":"2nd class","age":"adults","sex":"women","survived":"yes"},{"class":"2nd class","age":"adults","sex":"women","survived":"yes"},{"class":"2nd class","age":"adults","sex":"women","survived":"yes"},{"class":"2nd class","age":"adults","sex":"women","survived":"yes"},{"class":"2nd class","age":"adults","sex":"women","survived":"yes"},{"class":"2nd class","age":"adults","sex":"women","survived":"yes"},{"class":"2nd class","age":"adults","sex":"women","survived":"yes"},{"class":"2nd class","age":"adults","sex":"women","survived":"yes"},{"class":"2nd class","age":"adults","sex":"women","survived":"yes"},{"class":"2nd class","age":"adults","sex":"women","survived":"yes"},{"class":"2nd class","age":"adults","sex":"women","survived":"yes"},{"class":"2nd class","age":"adults","sex":"women","survived":"yes"},{"class":"2nd class","age":"adults","sex":"women","survived":"yes"},{"class":"2nd class","age":"adults","sex":"women","survived":"yes"},{"class":"2nd class","age":"adults","sex":"women","survived":"yes"},{"class":"2nd class","age":"adults","sex":"women","survived":"yes"},{"class":"2nd class","age":"adults","sex":"women","survived":"yes"},{"class":"2nd class","age":"adults","sex":"women","survived":"yes"},{"class":"2nd class","age":"adults","sex":"women","survived":"yes"},{"class":"2nd class","age":"adults","sex":"women","survived":"yes"},{"class":"2nd class","age":"adults","sex":"women","survived":"yes"},{"class":"2nd class","age":"adults","sex":"women","survived":"yes"},{"class":"2nd class","age":"adults","sex":"women","survived":"yes"},{"class":"2nd class","age":"adults","sex":"women","survived":"yes"},{"class":"2nd class","age":"adults","sex":"women","survived":"yes"},{"class":"2nd class","age":"adults","sex":"women","survived":"yes"},{"class":"2nd class","age":"adults","sex":"women","survived":"yes"},{"class":"2nd class","age":"adults","sex":"women","survived":"yes"},{"class":"2nd class","age":"adults","sex":"women","survived":"yes"},{"class":"2nd class","age":"adults","sex":"women","survived":"yes"},{"class":"2nd class","age":"adults","sex":"women","survived":"yes"},{"class":"2nd class","age":"adults","sex":"women","survived":"yes"},{"class":"2nd class","age":"adults","sex":"women","survived":"yes"},{"class":"2nd class","age":"adults","sex":"women","survived":"no"},{"class":"2nd class","age":"adults","sex":"women","survived":"no"},{"class":"2nd class","age":"adults","sex":"women","survived":"no"},{"class":"2nd class","age":"adults","sex":"women","survived":"no"},{"class":"2nd class","age":"adults","sex":"women","survived":"no"},{"class":"2nd class","age":"adults","sex":"women","survived":"no"},{"class":"2nd class","age":"adults","sex":"women","survived":"no"},{"class":"2nd class","age":"adults","sex":"women","survived":"no"},{"class":"2nd class","age":"adults","sex":"women","survived":"no"},{"class":"2nd class","age":"adults","sex":"women","survived":"no"},{"class":"2nd class","age":"adults","sex":"women","survived":"no"},{"class":"2nd class","age":"adults","sex":"women","survived":"no"},{"class":"2nd class","age":"adults","sex":"women","survived":"no"},{"class":"2nd class","age":"child","sex":"man","survived":"yes"},{"class":"2nd class","age":"child","sex":"man","survived":"yes"},{"class":"2nd class","age":"child","sex":"man","survived":"yes"},{"class":"2nd class","age":"child","sex":"man","survived":"yes"},{"class":"2nd class","age":"child","sex":"man","survived":"yes"},{"class":"2nd class","age":"child","sex":"man","survived":"yes"},{"class":"2nd class","age":"child","sex":"man","survived":"yes"},{"class":"2nd class","age":"child","sex":"man","survived":"yes"},{"class":"2nd class","age":"child","sex":"man","survived":"yes"},{"class":"2nd class","age":"child","sex":"man","survived":"yes"},{"class":"2nd class","age":"child","sex":"man","survived":"yes"},{"class":"2nd class","age":"child","sex":"women","survived":"yes"},{"class":"2nd class","age":"child","sex":"women","survived":"yes"},{"class":"2nd class","age":"child","sex":"women","survived":"yes"},{"class":"2nd class","age":"child","sex":"women","survived":"yes"},{"class":"2nd class","age":"child","sex":"women","survived":"yes"},{"class":"2nd class","age":"child","sex":"women","survived":"yes"},{"class":"2nd class","age":"child","sex":"women","survived":"yes"},{"class":"2nd class","age":"child","sex":"women","survived":"yes"},{"class":"2nd class","age":"child","sex":"women","survived":"yes"},{"class":"2nd class","age":"child","sex":"women","survived":"yes"},{"class":"2nd class","age":"child","sex":"women","survived":"yes"},{"class":"2nd class","age":"child","sex":"women","survived":"yes"},{"class":"2nd class","age":"child","sex":"women","survived":"yes"},{"class":"3rd class","age":"adults","sex":"man","survived":"yes"},{"class":"3rd class","age":"adults","sex":"man","survived":"yes"},{"class":"3rd class","age":"adults","sex":"man","survived":"yes"},{"class":"3rd class","age":"adults","sex":"man","survived":"yes"},{"class":"3rd class","age":"adults","sex":"man","survived":"yes"},{"class":"3rd class","age":"adults","sex":"man","survived":"yes"},{"class":"3rd class","age":"adults","sex":"man","survived":"yes"},{"class":"3rd class","age":"adults","sex":"man","survived":"yes"},{"class":"3rd class","age":"adults","sex":"man","survived":"yes"},{"class":"3rd class","age":"adults","sex":"man","survived":"yes"},{"class":"3rd class","age":"adults","sex":"man","survived":"yes"},{"class":"3rd class","age":"adults","sex":"man","survived":"yes"},{"class":"3rd class","age":"adults","sex":"man","survived":"yes"},{"class":"3rd class","age":"adults","sex":"man","survived":"yes"},{"class":"3rd class","age":"adults","sex":"man","survived":"yes"},{"class":"3rd class","age":"adults","sex":"man","survived":"yes"},{"class":"3rd class","age":"adults","sex":"man","survived":"yes"},{"class":"3rd class","age":"adults","sex":"man","survived":"yes"},{"class":"3rd class","age":"adults","sex":"man","survived":"yes"},{"class":"3rd class","age":"adults","sex":"man","survived":"yes"},{"class":"3rd class","age":"adults","sex":"man","survived":"yes"},{"class":"3rd class","age":"adults","sex":"man","survived":"yes"},{"class":"3rd class","age":"adults","sex":"man","survived":"yes"},{"class":"3rd class","age":"adults","sex":"man","survived":"yes"},{"class":"3rd class","age":"adults","sex":"man","survived":"yes"},{"class":"3rd class","age":"adults","sex":"man","survived":"yes"},{"class":"3rd class","age":"adults","sex":"man","survived":"yes"},{"class":"3rd class","age":"adults","sex":"man","survived":"yes"},{"class":"3rd class","age":"adults","sex":"man","survived":"yes"},{"class":"3rd class","age":"adults","sex":"man","survived":"yes"},{"class":"3rd class","age":"adults","sex":"man","survived":"yes"},{"class":"3rd class","age":"adults","sex":"man","survived":"yes"},{"class":"3rd class","age":"adults","sex":"man","survived":"yes"},{"class":"3rd class","age":"adults","sex":"man","survived":"yes"},{"class":"3rd class","age":"adults","sex":"man","survived":"yes"},{"class":"3rd class","age":"adults","sex":"man","survived":"yes"},{"class":"3rd class","age":"adults","sex":"man","survived":"yes"},{"class":"3rd class","age":"adults","sex":"man","survived":"yes"},{"class":"3rd class","age":"adults","sex":"man","survived":"yes"},{"class":"3rd class","age":"adults","sex":"man","survived":"yes"},{"class":"3rd class","age":"adults","sex":"man","survived":"yes"},{"class":"3rd class","age":"adults","sex":"man","survived":"yes"},{"class":"3rd class","age":"adults","sex":"man","survived":"yes"},{"class":"3rd class","age":"adults","sex":"man","survived":"yes"},{"class":"3rd class","age":"adults","sex":"man","survived":"yes"},{"class":"3rd class","age":"adults","sex":"man","survived":"yes"},{"class":"3rd class","age":"adults","sex":"man","survived":"yes"},{"class":"3rd class","age":"adults","sex":"man","survived":"yes"},{"class":"3rd class","age":"adults","sex":"man","survived":"yes"},{"class":"3rd class","age":"adults","sex":"man","survived":"yes"},{"class":"3rd class","age":"adults","sex":"man","survived":"yes"},{"class":"3rd class","age":"adults","sex":"man","survived":"yes"},{"class":"3rd class","age":"adults","sex":"man","survived":"yes"},{"class":"3rd class","age":"adults","sex":"man","survived":"yes"},{"class":"3rd class","age":"adults","sex":"man","survived":"yes"},{"class":"3rd class","age":"adults","sex":"man","survived":"yes"},{"class":"3rd class","age":"adults","sex":"man","survived":"yes"},{"class":"3rd class","age":"adults","sex":"man","survived":"yes"},{"class":"3rd class","age":"adults","sex":"man","survived":"yes"},{"class":"3rd class","age":"adults","sex":"man","survived":"yes"},{"class":"3rd class","age":"adults","sex":"man","survived":"yes"},{"class":"3rd class","age":"adults","sex":"man","survived":"yes"},{"class":"3rd class","age":"adults","sex":"man","survived":"yes"},{"class":"3rd class","age":"adults","sex":"man","survived":"yes"},{"class":"3rd class","age":"adults","sex":"man","survived":"yes"},{"class":"3rd class","age":"adults","sex":"man","survived":"yes"},{"class":"3rd class","age":"adults","sex":"man","survived":"yes"},{"class":"3rd class","age":"adults","sex":"man","survived":"yes"},{"class":"3rd class","age":"adults","sex":"man","survived":"yes"},{"class":"3rd class","age":"adults","sex":"man","survived":"yes"},{"class":"3rd class","age":"adults","sex":"man","survived":"yes"},{"class":"3rd class","age":"adults","sex":"man","survived":"yes"},{"class":"3rd class","age":"adults","sex":"man","survived":"yes"},{"class":"3rd class","age":"adults","sex":"man","survived":"yes"},{"class":"3rd class","age":"adults","sex":"man","survived":"yes"},{"class":"3rd class","age":"adults","sex":"man","survived":"no"},{"class":"3rd class","age":"adults","sex":"man","survived":"no"},{"class":"3rd class","age":"adults","sex":"man","survived":"no"},{"class":"3rd class","age":"adults","sex":"man","survived":"no"},{"class":"3rd class","age":"adults","sex":"man","survived":"no"},{"class":"3rd class","age":"adults","sex":"man","survived":"no"},{"class":"3rd class","age":"adults","sex":"man","survived":"no"},{"class":"3rd class","age":"adults","sex":"man","survived":"no"},{"class":"3rd class","age":"adults","sex":"man","survived":"no"},{"class":"3rd class","age":"adults","sex":"man","survived":"no"},{"class":"3rd class","age":"adults","sex":"man","survived":"no"},{"class":"3rd class","age":"adults","sex":"man","survived":"no"},{"class":"3rd class","age":"adults","sex":"man","survived":"no"},{"class":"3rd class","age":"adults","sex":"man","survived":"no"},{"class":"3rd class","age":"adults","sex":"man","survived":"no"},{"class":"3rd class","age":"adults","sex":"man","survived":"no"},{"class":"3rd class","age":"adults","sex":"man","survived":"no"},{"class":"3rd class","age":"adults","sex":"man","survived":"no"},{"class":"3rd class","age":"adults","sex":"man","survived":"no"},{"class":"3rd class","age":"adults","sex":"man","survived":"no"},{"class":"3rd class","age":"adults","sex":"man","survived":"no"},{"class":"3rd class","age":"adults","sex":"man","survived":"no"},{"class":"3rd class","age":"adults","sex":"man","survived":"no"},{"class":"3rd class","age":"adults","sex":"man","survived":"no"},{"class":"3rd class","age":"adults","sex":"man","survived":"no"},{"class":"3rd class","age":"adults","sex":"man","survived":"no"},{"class":"3rd class","age":"adults","sex":"man","survived":"no"},{"class":"3rd class","age":"adults","sex":"man","survived":"no"},{"class":"3rd class","age":"adults","sex":"man","survived":"no"},{"class":"3rd class","age":"adults","sex":"man","survived":"no"},{"class":"3rd class","age":"adults","sex":"man","survived":"no"},{"class":"3rd class","age":"adults","sex":"man","survived":"no"},{"class":"3rd class","age":"adults","sex":"man","survived":"no"},{"class":"3rd class","age":"adults","sex":"man","survived":"no"},{"class":"3rd class","age":"adults","sex":"man","survived":"no"},{"class":"3rd class","age":"adults","sex":"man","survived":"no"},{"class":"3rd class","age":"adults","sex":"man","survived":"no"},{"class":"3rd class","age":"adults","sex":"man","survived":"no"},{"class":"3rd class","age":"adults","sex":"man","survived":"no"},{"class":"3rd class","age":"adults","sex":"man","survived":"no"},{"class":"3rd class","age":"adults","sex":"man","survived":"no"},{"class":"3rd class","age":"adults","sex":"man","survived":"no"},{"class":"3rd class","age":"adults","sex":"man","survived":"no"},{"class":"3rd class","age":"adults","sex":"man","survived":"no"},{"class":"3rd class","age":"adults","sex":"man","survived":"no"},{"class":"3rd class","age":"adults","sex":"man","survived":"no"},{"class":"3rd class","age":"adults","sex":"man","survived":"no"},{"class":"3rd class","age":"adults","sex":"man","survived":"no"},{"class":"3rd class","age":"adults","sex":"man","survived":"no"},{"class":"3rd class","age":"adults","sex":"man","survived":"no"},{"class":"3rd class","age":"adults","sex":"man","survived":"no"},{"class":"3rd class","age":"adults","sex":"man","survived":"no"},{"class":"3rd class","age":"adults","sex":"man","survived":"no"},{"class":"3rd class","age":"adults","sex":"man","survived":"no"},{"class":"3rd class","age":"adults","sex":"man","survived":"no"},{"class":"3rd class","age":"adults","sex":"man","survived":"no"},{"class":"3rd class","age":"adults","sex":"man","survived":"no"},{"class":"3rd class","age":"adults","sex":"man","survived":"no"},{"class":"3rd class","age":"adults","sex":"man","survived":"no"},{"class":"3rd class","age":"adults","sex":"man","survived":"no"},{"class":"3rd class","age":"adults","sex":"man","survived":"no"},{"class":"3rd class","age":"adults","sex":"man","survived":"no"},{"class":"3rd class","age":"adults","sex":"man","survived":"no"},{"class":"3rd class","age":"adults","sex":"man","survived":"no"},{"class":"3rd class","age":"adults","sex":"man","survived":"no"},{"class":"3rd class","age":"adults","sex":"man","survived":"no"},{"class":"3rd class","age":"adults","sex":"man","survived":"no"},{"class":"3rd class","age":"adults","sex":"man","survived":"no"},{"class":"3rd class","age":"adults","sex":"man","survived":"no"},{"class":"3rd class","age":"adults","sex":"man","survived":"no"},{"class":"3rd class","age":"adults","sex":"man","survived":"no"},{"class":"3rd class","age":"adults","sex":"man","survived":"no"},{"class":"3rd class","age":"adults","sex":"man","survived":"no"},{"class":"3rd class","age":"adults","sex":"man","survived":"no"},{"class":"3rd class","age":"adults","sex":"man","survived":"no"},{"class":"3rd class","age":"adults","sex":"man","survived":"no"},{"class":"3rd class","age":"adults","sex":"man","survived":"no"},{"class":"3rd class","age":"adults","sex":"man","survived":"no"},{"class":"3rd class","age":"adults","sex":"man","survived":"no"},{"class":"3rd class","age":"adults","sex":"man","survived":"no"},{"class":"3rd class","age":"adults","sex":"man","survived":"no"},{"class":"3rd class","age":"adults","sex":"man","survived":"no"},{"class":"3rd class","age":"adults","sex":"man","survived":"no"},{"class":"3rd class","age":"adults","sex":"man","survived":"no"},{"class":"3rd class","age":"adults","sex":"man","survived":"no"},{"class":"3rd class","age":"adults","sex":"man","survived":"no"},{"class":"3rd class","age":"adults","sex":"man","survived":"no"},{"class":"3rd class","age":"adults","sex":"man","survived":"no"},{"class":"3rd class","age":"adults","sex":"man","survived":"no"},{"class":"3rd class","age":"adults","sex":"man","survived":"no"},{"class":"3rd class","age":"adults","sex":"man","survived":"no"},{"class":"3rd class","age":"adults","sex":"man","survived":"no"},{"class":"3rd class","age":"adults","sex":"man","survived":"no"},{"class":"3rd class","age":"adults","sex":"man","survived":"no"},{"class":"3rd class","age":"adults","sex":"man","survived":"no"},{"class":"3rd class","age":"adults","sex":"man","survived":"no"},{"class":"3rd class","age":"adults","sex":"man","survived":"no"},{"class":"3rd class","age":"adults","sex":"man","survived":"no"},{"class":"3rd class","age":"adults","sex":"man","survived":"no"},{"class":"3rd class","age":"adults","sex":"man","survived":"no"},{"class":"3rd class","age":"adults","sex":"man","survived":"no"},{"class":"3rd class","age":"adults","sex":"man","survived":"no"},{"class":"3rd class","age":"adults","sex":"man","survived":"no"},{"class":"3rd class","age":"adults","sex":"man","survived":"no"},{"class":"3rd class","age":"adults","sex":"man","survived":"no"},{"class":"3rd class","age":"adults","sex":"man","survived":"no"},{"class":"3rd class","age":"adults","sex":"man","survived":"no"},{"class":"3rd class","age":"adults","sex":"man","survived":"no"},{"class":"3rd class","age":"adults","sex":"man","survived":"no"},{"class":"3rd class","age":"adults","sex":"man","survived":"no"},{"class":"3rd class","age":"adults","sex":"man","survived":"no"},{"class":"3rd class","age":"adults","sex":"man","survived":"no"},{"class":"3rd class","age":"adults","sex":"man","survived":"no"},{"class":"3rd class","age":"adults","sex":"man","survived":"no"},{"class":"3rd class","age":"adults","sex":"man","survived":"no"},{"class":"3rd class","age":"adults","sex":"man","survived":"no"},{"class":"3rd class","age":"adults","sex":"man","survived":"no"},{"class":"3rd class","age":"adults","sex":"man","survived":"no"},{"class":"3rd class","age":"adults","sex":"man","survived":"no"},{"class":"3rd class","age":"adults","sex":"man","survived":"no"},{"class":"3rd class","age":"adults","sex":"man","survived":"no"},{"class":"3rd class","age":"adults","sex":"man","survived":"no"},{"class":"3rd class","age":"adults","sex":"man","survived":"no"},{"class":"3rd class","age":"adults","sex":"man","survived":"no"},{"class":"3rd class","age":"adults","sex":"man","survived":"no"},{"class":"3rd class","age":"adults","sex":"man","survived":"no"},{"class":"3rd class","age":"adults","sex":"man","survived":"no"},{"class":"3rd class","age":"adults","sex":"man","survived":"no"},{"class":"3rd class","age":"adults","sex":"man","survived":"no"},{"class":"3rd class","age":"adults","sex":"man","survived":"no"},{"class":"3rd class","age":"adults","sex":"man","survived":"no"},{"class":"3rd class","age":"adults","sex":"man","survived":"no"},{"class":"3rd class","age":"adults","sex":"man","survived":"no"},{"class":"3rd class","age":"adults","sex":"man","survived":"no"},{"class":"3rd class","age":"adults","sex":"man","survived":"no"},{"class":"3rd class","age":"adults","sex":"man","survived":"no"},{"class":"3rd class","age":"adults","sex":"man","survived":"no"},{"class":"3rd class","age":"adults","sex":"man","survived":"no"},{"class":"3rd class","age":"adults","sex":"man","survived":"no"},{"class":"3rd class","age":"adults","sex":"man","survived":"no"},{"class":"3rd class","age":"adults","sex":"man","survived":"no"},{"class":"3rd class","age":"adults","sex":"man","survived":"no"},{"class":"3rd class","age":"adults","sex":"man","survived":"no"},{"class":"3rd class","age":"adults","sex":"man","survived":"no"},{"class":"3rd class","age":"adults","sex":"man","survived":"no"},{"class":"3rd class","age":"adults","sex":"man","survived":"no"},{"class":"3rd class","age":"adults","sex":"man","survived":"no"},{"class":"3rd class","age":"adults","sex":"man","survived":"no"},{"class":"3rd class","age":"adults","sex":"man","survived":"no"},{"class":"3rd class","age":"adults","sex":"man","survived":"no"},{"class":"3rd class","age":"adults","sex":"man","survived":"no"},{"class":"3rd class","age":"adults","sex":"man","survived":"no"},{"class":"3rd class","age":"adults","sex":"man","survived":"no"},{"class":"3rd class","age":"adults","sex":"man","survived":"no"},{"class":"3rd class","age":"adults","sex":"man","survived":"no"},{"class":"3rd class","age":"adults","sex":"man","survived":"no"},{"class":"3rd class","age":"adults","sex":"man","survived":"no"},{"class":"3rd class","age":"adults","sex":"man","survived":"no"},{"class":"3rd class","age":"adults","sex":"man","survived":"no"},{"class":"3rd class","age":"adults","sex":"man","survived":"no"},{"class":"3rd class","age":"adults","sex":"man","survived":"no"},{"class":"3rd class","age":"adults","sex":"man","survived":"no"},{"class":"3rd class","age":"adults","sex":"man","survived":"no"},{"class":"3rd class","age":"adults","sex":"man","survived":"no"},{"class":"3rd class","age":"adults","sex":"man","survived":"no"},{"class":"3rd class","age":"adults","sex":"man","survived":"no"},{"class":"3rd class","age":"adults","sex":"man","survived":"no"},{"class":"3rd class","age":"adults","sex":"man","survived":"no"},{"class":"3rd class","age":"adults","sex":"man","survived":"no"},{"class":"3rd class","age":"adults","sex":"man","survived":"no"},{"class":"3rd class","age":"adults","sex":"man","survived":"no"},{"class":"3rd class","age":"adults","sex":"man","survived":"no"},{"class":"3rd class","age":"adults","sex":"man","survived":"no"},{"class":"3rd class","age":"adults","sex":"man","survived":"no"},{"class":"3rd class","age":"adults","sex":"man","survived":"no"},{"class":"3rd class","age":"adults","sex":"man","survived":"no"},{"class":"3rd class","age":"adults","sex":"man","survived":"no"},{"class":"3rd class","age":"adults","sex":"man","survived":"no"},{"class":"3rd class","age":"adults","sex":"man","survived":"no"},{"class":"3rd class","age":"adults","sex":"man","survived":"no"},{"class":"3rd class","age":"adults","sex":"man","survived":"no"},{"class":"3rd class","age":"adults","sex":"man","survived":"no"},{"class":"3rd class","age":"adults","sex":"man","survived":"no"},{"class":"3rd class","age":"adults","sex":"man","survived":"no"},{"class":"3rd class","age":"adults","sex":"man","survived":"no"},{"class":"3rd class","age":"adults","sex":"man","survived":"no"},{"class":"3rd class","age":"adults","sex":"man","survived":"no"},{"class":"3rd class","age":"adults","sex":"man","survived":"no"},{"class":"3rd class","age":"adults","sex":"man","survived":"no"},{"class":"3rd class","age":"adults","sex":"man","survived":"no"},{"class":"3rd class","age":"adults","sex":"man","survived":"no"},{"class":"3rd class","age":"adults","sex":"man","survived":"no"},{"class":"3rd class","age":"adults","sex":"man","survived":"no"},{"class":"3rd class","age":"adults","sex":"man","survived":"no"},{"class":"3rd class","age":"adults","sex":"man","survived":"no"},{"class":"3rd class","age":"adults","sex":"man","survived":"no"},{"class":"3rd class","age":"adults","sex":"man","survived":"no"},{"class":"3rd class","age":"adults","sex":"man","survived":"no"},{"class":"3rd class","age":"adults","sex":"man","survived":"no"},{"class":"3rd class","age":"adults","sex":"man","survived":"no"},{"class":"3rd class","age":"adults","sex":"man","survived":"no"},{"class":"3rd class","age":"adults","sex":"man","survived":"no"},{"class":"3rd class","age":"adults","sex":"man","survived":"no"},{"class":"3rd class","age":"adults","sex":"man","survived":"no"},{"class":"3rd class","age":"adults","sex":"man","survived":"no"},{"class":"3rd class","age":"adults","sex":"man","survived":"no"},{"class":"3rd class","age":"adults","sex":"man","survived":"no"},{"class":"3rd class","age":"adults","sex":"man","survived":"no"},{"class":"3rd class","age":"adults","sex":"man","survived":"no"},{"class":"3rd class","age":"adults","sex":"man","survived":"no"},{"class":"3rd class","age":"adults","sex":"man","survived":"no"},{"class":"3rd class","age":"adults","sex":"man","survived":"no"},{"class":"3rd class","age":"adults","sex":"man","survived":"no"},{"class":"3rd class","age":"adults","sex":"man","survived":"no"},{"class":"3rd class","age":"adults","sex":"man","survived":"no"},{"class":"3rd class","age":"adults","sex":"man","survived":"no"},{"class":"3rd class","age":"adults","sex":"man","survived":"no"},{"class":"3rd class","age":"adults","sex":"man","survived":"no"},{"class":"3rd class","age":"adults","sex":"man","survived":"no"},{"class":"3rd class","age":"adults","sex":"man","survived":"no"},{"class":"3rd class","age":"adults","sex":"man","survived":"no"},{"class":"3rd class","age":"adults","sex":"man","survived":"no"},{"class":"3rd class","age":"adults","sex":"man","survived":"no"},{"class":"3rd class","age":"adults","sex":"man","survived":"no"},{"class":"3rd class","age":"adults","sex":"man","survived":"no"},{"class":"3rd class","age":"adults","sex":"man","survived":"no"},{"class":"3rd class","age":"adults","sex":"man","survived":"no"},{"class":"3rd class","age":"adults","sex":"man","survived":"no"},{"class":"3rd class","age":"adults","sex":"man","survived":"no"},{"class":"3rd class","age":"adults","sex":"man","survived":"no"},{"class":"3rd class","age":"adults","sex":"man","survived":"no"},{"class":"3rd class","age":"adults","sex":"man","survived":"no"},{"class":"3rd class","age":"adults","sex":"man","survived":"no"},{"class":"3rd class","age":"adults","sex":"man","survived":"no"},{"class":"3rd class","age":"adults","sex":"man","survived":"no"},{"class":"3rd class","age":"adults","sex":"man","survived":"no"},{"class":"3rd class","age":"adults","sex":"man","survived":"no"},{"class":"3rd class","age":"adults","sex":"man","survived":"no"},{"class":"3rd class","age":"adults","sex":"man","survived":"no"},{"class":"3rd class","age":"adults","sex":"man","survived":"no"},{"class":"3rd class","age":"adults","sex":"man","survived":"no"},{"class":"3rd class","age":"adults","sex":"man","survived":"no"},{"class":"3rd class","age":"adults","sex":"man","survived":"no"},{"class":"3rd class","age":"adults","sex":"man","survived":"no"},{"class":"3rd class","age":"adults","sex":"man","survived":"no"},{"class":"3rd class","age":"adults","sex":"man","survived":"no"},{"class":"3rd class","age":"adults","sex":"man","survived":"no"},{"class":"3rd class","age":"adults","sex":"man","survived":"no"},{"class":"3rd class","age":"adults","sex":"man","survived":"no"},{"class":"3rd class","age":"adults","sex":"man","survived":"no"},{"class":"3rd class","age":"adults","sex":"man","survived":"no"},{"class":"3rd class","age":"adults","sex":"man","survived":"no"},{"class":"3rd class","age":"adults","sex":"man","survived":"no"},{"class":"3rd class","age":"adults","sex":"man","survived":"no"},{"class":"3rd class","age":"adults","sex":"man","survived":"no"},{"class":"3rd class","age":"adults","sex":"man","survived":"no"},{"class":"3rd class","age":"adults","sex":"man","survived":"no"},{"class":"3rd class","age":"adults","sex":"man","survived":"no"},{"class":"3rd class","age":"adults","sex":"man","survived":"no"},{"class":"3rd class","age":"adults","sex":"man","survived":"no"},{"class":"3rd class","age":"adults","sex":"man","survived":"no"},{"class":"3rd class","age":"adults","sex":"man","survived":"no"},{"class":"3rd class","age":"adults","sex":"man","survived":"no"},{"class":"3rd class","age":"adults","sex":"man","survived":"no"},{"class":"3rd class","age":"adults","sex":"man","survived":"no"},{"class":"3rd class","age":"adults","sex":"man","survived":"no"},{"class":"3rd class","age":"adults","sex":"man","survived":"no"},{"class":"3rd class","age":"adults","sex":"man","survived":"no"},{"class":"3rd class","age":"adults","sex":"man","survived":"no"},{"class":"3rd class","age":"adults","sex":"man","survived":"no"},{"class":"3rd class","age":"adults","sex":"man","survived":"no"},{"class":"3rd class","age":"adults","sex":"man","survived":"no"},{"class":"3rd class","age":"adults","sex":"man","survived":"no"},{"class":"3rd class","age":"adults","sex":"man","survived":"no"},{"class":"3rd class","age":"adults","sex":"man","survived":"no"},{"class":"3rd class","age":"adults","sex":"man","survived":"no"},{"class":"3rd class","age":"adults","sex":"man","survived":"no"},{"class":"3rd class","age":"adults","sex":"man","survived":"no"},{"class":"3rd class","age":"adults","sex":"man","survived":"no"},{"class":"3rd class","age":"adults","sex":"man","survived":"no"},{"class":"3rd class","age":"adults","sex":"man","survived":"no"},{"class":"3rd class","age":"adults","sex":"man","survived":"no"},{"class":"3rd class","age":"adults","sex":"man","survived":"no"},{"class":"3rd class","age":"adults","sex":"man","survived":"no"},{"class":"3rd class","age":"adults","sex":"man","survived":"no"},{"class":"3rd class","age":"adults","sex":"man","survived":"no"},{"class":"3rd class","age":"adults","sex":"man","survived":"no"},{"class":"3rd class","age":"adults","sex":"man","survived":"no"},{"class":"3rd class","age":"adults","sex":"man","survived":"no"},{"class":"3rd class","age":"adults","sex":"man","survived":"no"},{"class":"3rd class","age":"adults","sex":"man","survived":"no"},{"class":"3rd class","age":"adults","sex":"man","survived":"no"},{"class":"3rd class","age":"adults","sex":"man","survived":"no"},{"class":"3rd class","age":"adults","sex":"man","survived":"no"},{"class":"3rd class","age":"adults","sex":"man","survived":"no"},{"class":"3rd class","age":"adults","sex":"man","survived":"no"},{"class":"3rd class","age":"adults","sex":"man","survived":"no"},{"class":"3rd class","age":"adults","sex":"man","survived":"no"},{"class":"3rd class","age":"adults","sex":"man","survived":"no"},{"class":"3rd class","age":"adults","sex":"man","survived":"no"},{"class":"3rd class","age":"adults","sex":"man","survived":"no"},{"class":"3rd class","age":"adults","sex":"man","survived":"no"},{"class":"3rd class","age":"adults","sex":"man","survived":"no"},{"class":"3rd class","age":"adults","sex":"man","survived":"no"},{"class":"3rd class","age":"adults","sex":"man","survived":"no"},{"class":"3rd class","age":"adults","sex":"man","survived":"no"},{"class":"3rd class","age":"adults","sex":"man","survived":"no"},{"class":"3rd class","age":"adults","sex":"man","survived":"no"},{"class":"3rd class","age":"adults","sex":"man","survived":"no"},{"class":"3rd class","age":"adults","sex":"man","survived":"no"},{"class":"3rd class","age":"adults","sex":"man","survived":"no"},{"class":"3rd class","age":"adults","sex":"man","survived":"no"},{"class":"3rd class","age":"adults","sex":"man","survived":"no"},{"class":"3rd class","age":"adults","sex":"man","survived":"no"},{"class":"3rd class","age":"adults","sex":"man","survived":"no"},{"class":"3rd class","age":"adults","sex":"man","survived":"no"},{"class":"3rd class","age":"adults","sex":"man","survived":"no"},{"class":"3rd class","age":"adults","sex":"man","survived":"no"},{"class":"3rd class","age":"adults","sex":"man","survived":"no"},{"class":"3rd class","age":"adults","sex":"man","survived":"no"},{"class":"3rd class","age":"adults","sex":"man","survived":"no"},{"class":"3rd class","age":"adults","sex":"man","survived":"no"},{"class":"3rd class","age":"adults","sex":"man","survived":"no"},{"class":"3rd class","age":"adults","sex":"man","survived":"no"},{"class":"3rd class","age":"adults","sex":"man","survived":"no"},{"class":"3rd class","age":"adults","sex":"man","survived":"no"},{"class":"3rd class","age":"adults","sex":"man","survived":"no"},{"class":"3rd class","age":"adults","sex":"man","survived":"no"},{"class":"3rd class","age":"adults","sex":"man","survived":"no"},{"class":"3rd class","age":"adults","sex":"man","survived":"no"},{"class":"3rd class","age":"adults","sex":"man","survived":"no"},{"class":"3rd class","age":"adults","sex":"man","survived":"no"},{"class":"3rd class","age":"adults","sex":"man","survived":"no"},{"class":"3rd class","age":"adults","sex":"man","survived":"no"},{"class":"3rd class","age":"adults","sex":"man","survived":"no"},{"class":"3rd class","age":"adults","sex":"man","survived":"no"},{"class":"3rd class","age":"adults","sex":"man","survived":"no"},{"class":"3rd class","age":"adults","sex":"man","survived":"no"},{"class":"3rd class","age":"adults","sex":"man","survived":"no"},{"class":"3rd class","age":"adults","sex":"man","survived":"no"},{"class":"3rd class","age":"adults","sex":"man","survived":"no"},{"class":"3rd class","age":"adults","sex":"man","survived":"no"},{"class":"3rd class","age":"adults","sex":"man","survived":"no"},{"class":"3rd class","age":"adults","sex":"man","survived":"no"},{"class":"3rd class","age":"adults","sex":"man","survived":"no"},{"class":"3rd class","age":"adults","sex":"man","survived":"no"},{"class":"3rd class","age":"adults","sex":"man","survived":"no"},{"class":"3rd class","age":"adults","sex":"man","survived":"no"},{"class":"3rd class","age":"adults","sex":"man","survived":"no"},{"class":"3rd class","age":"adults","sex":"man","survived":"no"},{"class":"3rd class","age":"adults","sex":"man","survived":"no"},{"class":"3rd class","age":"adults","sex":"man","survived":"no"},{"class":"3rd class","age":"adults","sex":"man","survived":"no"},{"class":"3rd class","age":"adults","sex":"man","survived":"no"},{"class":"3rd class","age":"adults","sex":"man","survived":"no"},{"class":"3rd class","age":"adults","sex":"man","survived":"no"},{"class":"3rd class","age":"adults","sex":"man","survived":"no"},{"class":"3rd class","age":"adults","sex":"man","survived":"no"},{"class":"3rd class","age":"adults","sex":"man","survived":"no"},{"class":"3rd class","age":"adults","sex":"man","survived":"no"},{"class":"3rd class","age":"adults","sex":"man","survived":"no"},{"class":"3rd class","age":"adults","sex":"man","survived":"no"},{"class":"3rd class","age":"adults","sex":"man","survived":"no"},{"class":"3rd class","age":"adults","sex":"man","survived":"no"},{"class":"3rd class","age":"adults","sex":"man","survived":"no"},{"class":"3rd class","age":"adults","sex":"man","survived":"no"},{"class":"3rd class","age":"adults","sex":"man","survived":"no"},{"class":"3rd class","age":"adults","sex":"man","survived":"no"},{"class":"3rd class","age":"adults","sex":"man","survived":"no"},{"class":"3rd class","age":"adults","sex":"man","survived":"no"},{"class":"3rd class","age":"adults","sex":"man","survived":"no"},{"class":"3rd class","age":"adults","sex":"man","survived":"no"},{"class":"3rd class","age":"adults","sex":"man","survived":"no"},{"class":"3rd class","age":"adults","sex":"man","survived":"no"},{"class":"3rd class","age":"adults","sex":"man","survived":"no"},{"class":"3rd class","age":"adults","sex":"man","survived":"no"},{"class":"3rd class","age":"adults","sex":"man","survived":"no"},{"class":"3rd class","age":"adults","sex":"man","survived":"no"},{"class":"3rd class","age":"adults","sex":"man","survived":"no"},{"class":"3rd class","age":"adults","sex":"man","survived":"no"},{"class":"3rd class","age":"adults","sex":"man","survived":"no"},{"class":"3rd class","age":"adults","sex":"man","survived":"no"},{"class":"3rd class","age":"adults","sex":"man","survived":"no"},{"class":"3rd class","age":"adults","sex":"man","survived":"no"},{"class":"3rd class","age":"adults","sex":"man","survived":"no"},{"class":"3rd class","age":"adults","sex":"man","survived":"no"},{"class":"3rd class","age":"adults","sex":"man","survived":"no"},{"class":"3rd class","age":"adults","sex":"women","survived":"yes"},{"class":"3rd class","age":"adults","sex":"women","survived":"yes"},{"class":"3rd class","age":"adults","sex":"women","survived":"yes"},{"class":"3rd class","age":"adults","sex":"women","survived":"yes"},{"class":"3rd class","age":"adults","sex":"women","survived":"yes"},{"class":"3rd class","age":"adults","sex":"women","survived":"yes"},{"class":"3rd class","age":"adults","sex":"women","survived":"yes"},{"class":"3rd class","age":"adults","sex":"women","survived":"yes"},{"class":"3rd class","age":"adults","sex":"women","survived":"yes"},{"class":"3rd class","age":"adults","sex":"women","survived":"yes"},{"class":"3rd class","age":"adults","sex":"women","survived":"yes"},{"class":"3rd class","age":"adults","sex":"women","survived":"yes"},{"class":"3rd class","age":"adults","sex":"women","survived":"yes"},{"class":"3rd class","age":"adults","sex":"women","survived":"yes"},{"class":"3rd class","age":"adults","sex":"women","survived":"yes"},{"class":"3rd class","age":"adults","sex":"women","survived":"yes"},{"class":"3rd class","age":"adults","sex":"women","survived":"yes"},{"class":"3rd class","age":"adults","sex":"women","survived":"yes"},{"class":"3rd class","age":"adults","sex":"women","survived":"yes"},{"class":"3rd class","age":"adults","sex":"women","survived":"yes"},{"class":"3rd class","age":"adults","sex":"women","survived":"yes"},{"class":"3rd class","age":"adults","sex":"women","survived":"yes"},{"class":"3rd class","age":"adults","sex":"women","survived":"yes"},{"class":"3rd class","age":"adults","sex":"women","survived":"yes"},{"class":"3rd class","age":"adults","sex":"women","survived":"yes"},{"class":"3rd class","age":"adults","sex":"women","survived":"yes"},{"class":"3rd class","age":"adults","sex":"women","survived":"yes"},{"class":"3rd class","age":"adults","sex":"women","survived":"yes"},{"class":"3rd class","age":"adults","sex":"women","survived":"yes"},{"class":"3rd class","age":"adults","sex":"women","survived":"yes"},{"class":"3rd class","age":"adults","sex":"women","survived":"yes"},{"class":"3rd class","age":"adults","sex":"women","survived":"yes"},{"class":"3rd class","age":"adults","sex":"women","survived":"yes"},{"class":"3rd class","age":"adults","sex":"women","survived":"yes"},{"class":"3rd class","age":"adults","sex":"women","survived":"yes"},{"class":"3rd class","age":"adults","sex":"women","survived":"yes"},{"class":"3rd class","age":"adults","sex":"women","survived":"yes"},{"class":"3rd class","age":"adults","sex":"women","survived":"yes"},{"class":"3rd class","age":"adults","sex":"women","survived":"yes"},{"class":"3rd class","age":"adults","sex":"women","survived":"yes"},{"class":"3rd class","age":"adults","sex":"women","survived":"yes"},{"class":"3rd class","age":"adults","sex":"women","survived":"yes"},{"class":"3rd class","age":"adults","sex":"women","survived":"yes"},{"class":"3rd class","age":"adults","sex":"women","survived":"yes"},{"class":"3rd class","age":"adults","sex":"women","survived":"yes"},{"class":"3rd class","age":"adults","sex":"women","survived":"yes"},{"class":"3rd class","age":"adults","sex":"women","survived":"yes"},{"class":"3rd class","age":"adults","sex":"women","survived":"yes"},{"class":"3rd class","age":"adults","sex":"women","survived":"yes"},{"class":"3rd class","age":"adults","sex":"women","survived":"yes"},{"class":"3rd class","age":"adults","sex":"women","survived":"yes"},{"class":"3rd class","age":"adults","sex":"women","survived":"yes"},{"class":"3rd class","age":"adults","sex":"women","survived":"yes"},{"class":"3rd class","age":"adults","sex":"women","survived":"yes"},{"class":"3rd class","age":"adults","sex":"women","survived":"yes"},{"class":"3rd class","age":"adults","sex":"women","survived":"yes"},{"class":"3rd class","age":"adults","sex":"women","survived":"yes"},{"class":"3rd class","age":"adults","sex":"women","survived":"yes"},{"class":"3rd class","age":"adults","sex":"women","survived":"yes"},{"class":"3rd class","age":"adults","sex":"women","survived":"yes"},{"class":"3rd class","age":"adults","sex":"women","survived":"yes"},{"class":"3rd class","age":"adults","sex":"women","survived":"yes"},{"class":"3rd class","age":"adults","sex":"women","survived":"yes"},{"class":"3rd class","age":"adults","sex":"women","survived":"yes"},{"class":"3rd class","age":"adults","sex":"women","survived":"yes"},{"class":"3rd class","age":"adults","sex":"women","survived":"yes"},{"class":"3rd class","age":"adults","sex":"women","survived":"yes"},{"class":"3rd class","age":"adults","sex":"women","survived":"yes"},{"class":"3rd class","age":"adults","sex":"women","survived":"yes"},{"class":"3rd class","age":"adults","sex":"women","survived":"yes"},{"class":"3rd class","age":"adults","sex":"women","survived":"yes"},{"class":"3rd class","age":"adults","sex":"women","survived":"yes"},{"class":"3rd class","age":"adults","sex":"women","survived":"yes"},{"class":"3rd class","age":"adults","sex":"women","survived":"yes"},{"class":"3rd class","age":"adults","sex":"women","survived":"yes"},{"class":"3rd class","age":"adults","sex":"women","survived":"yes"},{"class":"3rd class","age":"adults","sex":"women","survived":"no"},{"class":"3rd class","age":"adults","sex":"women","survived":"no"},{"class":"3rd class","age":"adults","sex":"women","survived":"no"},{"class":"3rd class","age":"adults","sex":"women","survived":"no"},{"class":"3rd class","age":"adults","sex":"women","survived":"no"},{"class":"3rd class","age":"adults","sex":"women","survived":"no"},{"class":"3rd class","age":"adults","sex":"women","survived":"no"},{"class":"3rd class","age":"adults","sex":"women","survived":"no"},{"class":"3rd class","age":"adults","sex":"women","survived":"no"},{"class":"3rd class","age":"adults","sex":"women","survived":"no"},{"class":"3rd class","age":"adults","sex":"women","survived":"no"},{"class":"3rd class","age":"adults","sex":"women","survived":"no"},{"class":"3rd class","age":"adults","sex":"women","survived":"no"},{"class":"3rd class","age":"adults","sex":"women","survived":"no"},{"class":"3rd class","age":"adults","sex":"women","survived":"no"},{"class":"3rd class","age":"adults","sex":"women","survived":"no"},{"class":"3rd class","age":"adults","sex":"women","survived":"no"},{"class":"3rd class","age":"adults","sex":"women","survived":"no"},{"class":"3rd class","age":"adults","sex":"women","survived":"no"},{"class":"3rd class","age":"adults","sex":"women","survived":"no"},{"class":"3rd class","age":"adults","sex":"women","survived":"no"},{"class":"3rd class","age":"adults","sex":"women","survived":"no"},{"class":"3rd class","age":"adults","sex":"women","survived":"no"},{"class":"3rd class","age":"adults","sex":"women","survived":"no"},{"class":"3rd class","age":"adults","sex":"women","survived":"no"},{"class":"3rd class","age":"adults","sex":"women","survived":"no"},{"class":"3rd class","age":"adults","sex":"women","survived":"no"},{"class":"3rd class","age":"adults","sex":"women","survived":"no"},{"class":"3rd class","age":"adults","sex":"women","survived":"no"},{"class":"3rd class","age":"adults","sex":"women","survived":"no"},{"class":"3rd class","age":"adults","sex":"women","survived":"no"},{"class":"3rd class","age":"adults","sex":"women","survived":"no"},{"class":"3rd class","age":"adults","sex":"women","survived":"no"},{"class":"3rd class","age":"adults","sex":"women","survived":"no"},{"class":"3rd class","age":"adults","sex":"women","survived":"no"},{"class":"3rd class","age":"adults","sex":"women","survived":"no"},{"class":"3rd class","age":"adults","sex":"women","survived":"no"},{"class":"3rd class","age":"adults","sex":"women","survived":"no"},{"class":"3rd class","age":"adults","sex":"women","survived":"no"},{"class":"3rd class","age":"adults","sex":"women","survived":"no"},{"class":"3rd class","age":"adults","sex":"women","survived":"no"},{"class":"3rd class","age":"adults","sex":"women","survived":"no"},{"class":"3rd class","age":"adults","sex":"women","survived":"no"},{"class":"3rd class","age":"adults","sex":"women","survived":"no"},{"class":"3rd class","age":"adults","sex":"women","survived":"no"},{"class":"3rd class","age":"adults","sex":"women","survived":"no"},{"class":"3rd class","age":"adults","sex":"women","survived":"no"},{"class":"3rd class","age":"adults","sex":"women","survived":"no"},{"class":"3rd class","age":"adults","sex":"women","survived":"no"},{"class":"3rd class","age":"adults","sex":"women","survived":"no"},{"class":"3rd class","age":"adults","sex":"women","survived":"no"},{"class":"3rd class","age":"adults","sex":"women","survived":"no"},{"class":"3rd class","age":"adults","sex":"women","survived":"no"},{"class":"3rd class","age":"adults","sex":"women","survived":"no"},{"class":"3rd class","age":"adults","sex":"women","survived":"no"},{"class":"3rd class","age":"adults","sex":"women","survived":"no"},{"class":"3rd class","age":"adults","sex":"women","survived":"no"},{"class":"3rd class","age":"adults","sex":"women","survived":"no"},{"class":"3rd class","age":"adults","sex":"women","survived":"no"},{"class":"3rd class","age":"adults","sex":"women","survived":"no"},{"class":"3rd class","age":"adults","sex":"women","survived":"no"},{"class":"3rd class","age":"adults","sex":"women","survived":"no"},{"class":"3rd class","age":"adults","sex":"women","survived":"no"},{"class":"3rd class","age":"adults","sex":"women","survived":"no"},{"class":"3rd class","age":"adults","sex":"women","survived":"no"},{"class":"3rd class","age":"adults","sex":"women","survived":"no"},{"class":"3rd class","age":"adults","sex":"women","survived":"no"},{"class":"3rd class","age":"adults","sex":"women","survived":"no"},{"class":"3rd class","age":"adults","sex":"women","survived":"no"},{"class":"3rd class","age":"adults","sex":"women","survived":"no"},{"class":"3rd class","age":"adults","sex":"women","survived":"no"},{"class":"3rd class","age":"adults","sex":"women","survived":"no"},{"class":"3rd class","age":"adults","sex":"women","survived":"no"},{"class":"3rd class","age":"adults","sex":"women","survived":"no"},{"class":"3rd class","age":"adults","sex":"women","survived":"no"},{"class":"3rd class","age":"adults","sex":"women","survived":"no"},{"class":"3rd class","age":"adults","sex":"women","survived":"no"},{"class":"3rd class","age":"adults","sex":"women","survived":"no"},{"class":"3rd class","age":"adults","sex":"women","survived":"no"},{"class":"3rd class","age":"adults","sex":"women","survived":"no"},{"class":"3rd class","age":"adults","sex":"women","survived":"no"},{"class":"3rd class","age":"adults","sex":"women","survived":"no"},{"class":"3rd class","age":"adults","sex":"women","survived":"no"},{"class":"3rd class","age":"adults","sex":"women","survived":"no"},{"class":"3rd class","age":"adults","sex":"women","survived":"no"},{"class":"3rd class","age":"adults","sex":"women","survived":"no"},{"class":"3rd class","age":"adults","sex":"women","survived":"no"},{"class":"3rd class","age":"adults","sex":"women","survived":"no"},{"class":"3rd class","age":"adults","sex":"women","survived":"no"},{"class":"3rd class","age":"child","sex":"man","survived":"yes"},{"class":"3rd class","age":"child","sex":"man","survived":"yes"},{"class":"3rd class","age":"child","sex":"man","survived":"yes"},{"class":"3rd class","age":"child","sex":"man","survived":"yes"},{"class":"3rd class","age":"child","sex":"man","survived":"yes"},{"class":"3rd class","age":"child","sex":"man","survived":"yes"},{"class":"3rd class","age":"child","sex":"man","survived":"yes"},{"class":"3rd class","age":"child","sex":"man","survived":"yes"},{"class":"3rd class","age":"child","sex":"man","survived":"yes"},{"class":"3rd class","age":"child","sex":"man","survived":"yes"},{"class":"3rd class","age":"child","sex":"man","survived":"yes"},{"class":"3rd class","age":"child","sex":"man","survived":"yes"},{"class":"3rd class","age":"child","sex":"man","survived":"yes"},{"class":"3rd class","age":"child","sex":"man","survived":"no"},{"class":"3rd class","age":"child","sex":"man","survived":"no"},{"class":"3rd class","age":"child","sex":"man","survived":"no"},{"class":"3rd class","age":"child","sex":"man","survived":"no"},{"class":"3rd class","age":"child","sex":"man","survived":"no"},{"class":"3rd class","age":"child","sex":"man","survived":"no"},{"class":"3rd class","age":"child","sex":"man","survived":"no"},{"class":"3rd class","age":"child","sex":"man","survived":"no"},{"class":"3rd class","age":"child","sex":"man","survived":"no"},{"class":"3rd class","age":"child","sex":"man","survived":"no"},{"class":"3rd class","age":"child","sex":"man","survived":"no"},{"class":"3rd class","age":"child","sex":"man","survived":"no"},{"class":"3rd class","age":"child","sex":"man","survived":"no"},{"class":"3rd class","age":"child","sex":"man","survived":"no"},{"class":"3rd class","age":"child","sex":"man","survived":"no"},{"class":"3rd class","age":"child","sex":"man","survived":"no"},{"class":"3rd class","age":"child","sex":"man","survived":"no"},{"class":"3rd class","age":"child","sex":"man","survived":"no"},{"class":"3rd class","age":"child","sex":"man","survived":"no"},{"class":"3rd class","age":"child","sex":"man","survived":"no"},{"class":"3rd class","age":"child","sex":"man","survived":"no"},{"class":"3rd class","age":"child","sex":"man","survived":"no"},{"class":"3rd class","age":"child","sex":"man","survived":"no"},{"class":"3rd class","age":"child","sex":"man","survived":"no"},{"class":"3rd class","age":"child","sex":"man","survived":"no"},{"class":"3rd class","age":"child","sex":"man","survived":"no"},{"class":"3rd class","age":"child","sex":"man","survived":"no"},{"class":"3rd class","age":"child","sex":"man","survived":"no"},{"class":"3rd class","age":"child","sex":"man","survived":"no"},{"class":"3rd class","age":"child","sex":"man","survived":"no"},{"class":"3rd class","age":"child","sex":"man","survived":"no"},{"class":"3rd class","age":"child","sex":"man","survived":"no"},{"class":"3rd class","age":"child","sex":"man","survived":"no"},{"class":"3rd class","age":"child","sex":"man","survived":"no"},{"class":"3rd class","age":"child","sex":"man","survived":"no"},{"class":"3rd class","age":"child","sex":"women","survived":"yes"},{"class":"3rd class","age":"child","sex":"women","survived":"yes"},{"class":"3rd class","age":"child","sex":"women","survived":"yes"},{"class":"3rd class","age":"child","sex":"women","survived":"yes"},{"class":"3rd class","age":"child","sex":"women","survived":"yes"},{"class":"3rd class","age":"child","sex":"women","survived":"yes"},{"class":"3rd class","age":"child","sex":"women","survived":"yes"},{"class":"3rd class","age":"child","sex":"women","survived":"yes"},{"class":"3rd class","age":"child","sex":"women","survived":"yes"},{"class":"3rd class","age":"child","sex":"women","survived":"yes"},{"class":"3rd class","age":"child","sex":"women","survived":"yes"},{"class":"3rd class","age":"child","sex":"women","survived":"yes"},{"class":"3rd class","age":"child","sex":"women","survived":"yes"},{"class":"3rd class","age":"child","sex":"women","survived":"yes"},{"class":"3rd class","age":"child","sex":"women","survived":"no"},{"class":"3rd class","age":"child","sex":"women","survived":"no"},{"class":"3rd class","age":"child","sex":"women","survived":"no"},{"class":"3rd class","age":"child","sex":"women","survived":"no"},{"class":"3rd class","age":"child","sex":"women","survived":"no"},{"class":"3rd class","age":"child","sex":"women","survived":"no"},{"class":"3rd class","age":"child","sex":"women","survived":"no"},{"class":"3rd class","age":"child","sex":"women","survived":"no"},{"class":"3rd class","age":"child","sex":"women","survived":"no"},{"class":"3rd class","age":"child","sex":"women","survived":"no"},{"class":"3rd class","age":"child","sex":"women","survived":"no"},{"class":"3rd class","age":"child","sex":"women","survived":"no"},{"class":"3rd class","age":"child","sex":"women","survived":"no"},{"class":"3rd class","age":"child","sex":"women","survived":"no"},{"class":"3rd class","age":"child","sex":"women","survived":"no"},{"class":"3rd class","age":"child","sex":"women","survived":"no"},{"class":"3rd class","age":"child","sex":"women","survived":"no"}]