[{"state":"Alabama","abbr":"AL","fips":1,"pop2010":4779736,"pop2000":4447100,"homeownership":71.1,"multiunit":15.5,"income":22984,"med_income":42081,"poverty":17.1,"fed_spend":11.7261340375,"land_area":50645.33,"smoke":24.8,"murder":8.2,"robbery":141.4,"agg_assault":5.2,"larceny":55.4,"motor_theft":6.0,"soc_sec":18.5,"nuclear":16.3,"coal":56.6,"tr_deaths":23.7,"tr_deaths_no_alc":1.3,"unempl":7.6},{"state":"Alaska","abbr":"AK","fips":2,"pop2010":710231,"pop2000":626932,"homeownership":64.7,"multiunit":24.6,"income":30726,"med_income":66521,"poverty":9.5,"fed_spend":16.7865680321,"land_area":570640.95,"smoke":25.0,"murder":4.8,"robbery":80.9,"agg_assault":65.5,"larceny":366.0,"motor_theft":55.1,"soc_sec":8.9,"nuclear":0.0,"coal":9.5,"tr_deaths":10.1,"tr_deaths_no_alc":7.3,"unempl":7.1},{"state":"Arizona","abbr":"AZ","fips":4,"pop2010":6392017,"pop2000":5130632,"homeownership":67.4,"multiunit":20.7,"income":25680,"med_income":50448,"poverty":15.3,"fed_spend":9.8471275968,"land_area":113594.08,"smoke":20.4,"murder":7.5,"robbery":144.4,"agg_assault":5.1,"larceny":46.4,"motor_theft":14.5,"soc_sec":13.9,"nuclear":15.6,"coal":39.6,"tr_deaths":18.4,"tr_deaths_no_alc":0.9,"unempl":8.7},{"state":"Arkansas","abbr":"AR","fips":5,"pop2010":2915918,"pop2000":2673400,"homeownership":67.7,"multiunit":15.2,"income":21274,"med_income":39267,"poverty":18.0,"fed_spend":9.6111855683,"land_area":52035.48,"smoke":23.5,"murder":6.7,"robbery":91.1,"agg_assault":13.3,"larceny":93.0,"motor_theft":9.0,"soc_sec":18.7,"nuclear":13.0,"coal":48.2,"tr_deaths":22.2,"tr_deaths_no_alc":2.2,"unempl":7.6},{"state":"California","abbr":"CA","fips":6,"pop2010":37253956,"pop2000":33871648,"homeownership":57.4,"multiunit":30.7,"income":29188,"med_income":60883,"poverty":13.7,"fed_spend":8.8857910553,"land_area":155779.22,"smoke":15.2,"murder":6.9,"robbery":176.1,"agg_assault":0.9,"larceny":5.1,"motor_theft":1.9,"soc_sec":11.8,"nuclear":7.0,"coal":1.1,"tr_deaths":11.6,"tr_deaths_no_alc":0.2,"unempl":10.9},{"state":"Colorado","abbr":"CO","fips":8,"pop2010":5029196,"pop2000":4301261,"homeownership":67.6,"multiunit":25.6,"income":30151,"med_income":56456,"poverty":12.2,"fed_spend":9.1522945218,"land_area":103641.89,"smoke":19.9,"murder":3.7,"robbery":84.6,"agg_assault":5.3,"larceny":54.4,"motor_theft":11.1,"soc_sec":11.4,"nuclear":0.0,"coal":71.7,"tr_deaths":12.0,"tr_deaths_no_alc":1.2,"unempl":7.8},{"state":"Connecticut","abbr":"CT","fips":9,"pop2010":3574097,"pop2000":3405565,"homeownership":69.2,"multiunit":34.6,"income":36775,"med_income":67740,"poverty":9.2,"fed_spend":14.8344720359,"land_area":4842.36,"smoke":16.5,"murder":2.9,"robbery":113.0,"agg_assault":3.9,"larceny":51.0,"motor_theft":8.3,"soc_sec":16.3,"nuclear":25.6,"coal":11.9,"tr_deaths":7.7,"tr_deaths_no_alc":1.6,"unempl":7.8},{"state":"Delaware","abbr":"DE","fips":10,"pop2010":897934,"pop2000":783600,"homeownership":73.6,"multiunit":17.7,"income":29007,"med_income":57599,"poverty":11.0,"fed_spend":8.8895386521,"land_area":1948.54,"smoke":20.7,"murder":4.4,"robbery":154.8,"agg_assault":47.7,"larceny":238.8,"motor_theft":31.0,"soc_sec":16.6,"nuclear":0.0,"coal":59.4,"tr_deaths":14.9,"tr_deaths_no_alc":5.7,"unempl":7.0},{"state":"District of Columbia","abbr":"DC","fips":11,"pop2010":601723,"pop2000":572059,"homeownership":43.5,"multiunit":61.7,"income":42078,"med_income":58526,"poverty":18.5,"fed_spend":100.9090661318,"land_area":61.05,"smoke":20.1,"murder":35.4,"robbery":672.1,"agg_assault":119.9,"larceny":447.9,"motor_theft":233.0,"soc_sec":12.0,"nuclear":0.0,"coal":0.0,"tr_deaths":8.0,"tr_deaths_no_alc":7.5,"unempl":9.9},{"state":"Florida","abbr":"FL","fips":12,"pop2010":18801310,"pop2000":15982378,"homeownership":69.7,"multiunit":30.0,"income":26551,"med_income":47661,"poverty":13.8,"fed_spend":9.6210014621,"land_area":53624.76,"smoke":21.6,"murder":5.0,"robbery":169.4,"agg_assault":2.6,"larceny":14.1,"motor_theft":2.3,"soc_sec":18.0,"nuclear":7.3,"coal":28.4,"tr_deaths":18.8,"tr_deaths_no_alc":0.3,"unempl":9.4},{"state":"Georgia","abbr":"GA","fips":13,"pop2010":9687653,"pop2000":8186453,"homeownership":67.2,"multiunit":20.5,"income":25134,"med_income":49347,"poverty":15.7,"fed_spend":8.8822446469,"land_area":57513.49,"smoke":22.2,"murder":6.2,"robbery":154.8,"agg_assault":2.7,"larceny":28.4,"motor_theft":5.1,"soc_sec":12.3,"nuclear":11.1,"coal":63.8,"tr_deaths":17.8,"tr_deaths_no_alc":0.7,"unempl":9.1},{"state":"Hawaii","abbr":"HI","fips":15,"pop2010":1360301,"pop2000":1211537,"homeownership":59.3,"multiunit":39.2,"income":28882,"med_income":66420,"poverty":9.6,"fed_spend":13.9567676566,"land_area":6422.63,"smoke":17.1,"murder":1.9,"robbery":78.5,"agg_assault":10.9,"larceny":243.2,"motor_theft":52.7,"soc_sec":14.6,"nuclear":0.0,"coal":14.2,"tr_deaths":10.3,"tr_deaths_no_alc":3.6,"unempl":6.4},{"state":"Idaho","abbr":"ID","fips":16,"pop2010":1567582,"pop2000":1293953,"homeownership":71.0,"multiunit":14.9,"income":22518,"med_income":46423,"poverty":13.6,"fed_spend":8.8244378922,"land_area":82643.12,"smoke":17.9,"murder":2.4,"robbery":18.6,"agg_assault":12.5,"larceny":123.2,"motor_theft":12.9,"soc_sec":14.0,"nuclear":0.0,"coal":0.9,"tr_deaths":17.5,"tr_deaths_no_alc":4.3,"unempl":8.0},{"state":"Illinois","abbr":"IL","fips":17,"pop2010":12830632,"pop2000":12419293,"homeownership":69.2,"multiunit":33.0,"income":28782,"med_income":55735,"poverty":12.6,"fed_spend":8.5170122563,"land_area":55518.93,"smoke":19.9,"murder":6.0,"robbery":181.7,"agg_assault":2.6,"larceny":16.9,"motor_theft":2.4,"soc_sec":14.7,"nuclear":26.8,"coal":47.5,"tr_deaths":10.6,"tr_deaths_no_alc":0.4,"unempl":9.1},{"state":"Indiana","abbr":"IN","fips":18,"pop2010":6483802,"pop2000":6080485,"homeownership":71.5,"multiunit":18.6,"income":24058,"med_income":47697,"poverty":13.5,"fed_spend":9.4497736051,"land_area":35826.11,"smoke":27.3,"murder":5.7,"robbery":108.6,"agg_assault":2.8,"larceny":37.2,"motor_theft":5.3,"soc_sec":16.0,"nuclear":0.0,"coal":94.2,"tr_deaths":14.5,"tr_deaths_no_alc":1.0,"unempl":8.4},{"state":"Iowa","abbr":"IA","fips":19,"pop2010":3046355,"pop2000":2926324,"homeownership":73.2,"multiunit":18.6,"income":25335,"med_income":48872,"poverty":11.6,"fed_spend":9.502676149,"land_area":55857.13,"smoke":20.4,"murder":1.3,"robbery":38.9,"agg_assault":7.3,"larceny":67.1,"motor_theft":6.1,"soc_sec":17.9,"nuclear":5.2,"coal":77.6,"tr_deaths":14.8,"tr_deaths_no_alc":2.4,"unempl":5.3},{"state":"Kansas","abbr":"KS","fips":20,"pop2010":2853118,"pop2000":2688418,"homeownership":69.4,"multiunit":17.4,"income":25907,"med_income":49424,"poverty":12.4,"fed_spend":10.3647045092,"land_area":81758.72,"smoke":17.8,"murder":null,"robbery":null,"agg_assault":null,"larceny":null,"motor_theft":null,"soc_sec":15.7,"nuclear":10.6,"coal":75.2,"tr_deaths":15.0,"tr_deaths_no_alc":2.3,"unempl":6.1},{"state":"Kentucky","abbr":"KY","fips":21,"pop2010":4339367,"pop2000":4041769,"homeownership":69.9,"multiunit":17.7,"income":22515,"med_income":41576,"poverty":17.7,"fed_spend":12.963916857,"land_area":39486.34,"smoke":28.7,"murder":null,"robbery":null,"agg_assault":null,"larceny":null,"motor_theft":null,"soc_sec":18.1,"nuclear":0.0,"coal":91.1,"tr_deaths":22.7,"tr_deaths_no_alc":1.6,"unempl":8.7},{"state":"Louisiana","abbr":"LA","fips":22,"pop2010":4533372,"pop2000":4468976,"homeownership":68.2,"multiunit":17.8,"income":23094,"med_income":43445,"poverty":18.1,"fed_spend":11.6113667707,"land_area":43203.9,"smoke":22.6,"murder":9.9,"robbery":118.0,"agg_assault":9.6,"larceny":55.0,"motor_theft":7.0,"soc_sec":16.3,"nuclear":7.9,"coal":24.9,"tr_deaths":21.1,"tr_deaths_no_alc":1.3,"unempl":7.0},{"state":"Maine","abbr":"ME","fips":23,"pop2010":1328361,"pop2000":1274923,"homeownership":73.1,"multiunit":19.4,"income":25385,"med_income":46933,"poverty":12.6,"fed_spend":10.8876194047,"land_area":30842.92,"smoke":20.9,"murder":1.4,"robbery":24.4,"agg_assault":4.6,"larceny":138.0,"motor_theft":7.7,"soc_sec":19.9,"nuclear":0.0,"coal":1.7,"tr_deaths":12.7,"tr_deaths_no_alc":4.9,"unempl":7.1},{"state":"Maryland","abbr":"MD","fips":24,"pop2010":5773552,"pop2000":5296486,"homeownership":69.0,"multiunit":25.7,"income":34849,"med_income":70647,"poverty":8.6,"fed_spend":16.6398380061,"land_area":9707.24,"smoke":19.0,"murder":9.9,"robbery":256.7,"agg_assault":7.2,"larceny":39.7,"motor_theft":10.5,"soc_sec":13.2,"nuclear":13.9,"coal":55.7,"tr_deaths":10.6,"tr_deaths_no_alc":1.1,"unempl":6.5},{"state":"Massachusetts","abbr":"MA","fips":25,"pop2010":6547629,"pop2000":6349097,"homeownership":64.0,"multiunit":41.7,"income":33966,"med_income":64509,"poverty":10.5,"fed_spend":12.4884598685,"land_area":7800.06,"smoke":18.1,"murder":2.7,"robbery":119.0,"agg_assault":4.7,"larceny":23.3,"motor_theft":4.5,"soc_sec":16.3,"nuclear":4.9,"coal":25.3,"tr_deaths":6.8,"tr_deaths_no_alc":0.9,"unempl":6.9},{"state":"Michigan","abbr":"MI","fips":26,"pop2010":9883640,"pop2000":9938444,"homeownership":74.2,"multiunit":18.0,"income":25135,"med_income":48432,"poverty":14.8,"fed_spend":9.2391201015,"land_area":56538.9,"smoke":22.1,"murder":6.1,"robbery":131.8,"agg_assault":3.7,"larceny":19.4,"motor_theft":4.8,"soc_sec":17.4,"nuclear":13.1,"coal":57.8,"tr_deaths":11.4,"tr_deaths_no_alc":0.6,"unempl":8.8},{"state":"Minnesota","abbr":"MN","fips":27,"pop2010":5303925,"pop2000":4919479,"homeownership":74.2,"multiunit":21.5,"income":29582,"med_income":57243,"poverty":10.6,"fed_spend":8.359493017,"land_area":79626.74,"smoke":20.0,"murder":2.2,"robbery":92.0,"agg_assault":3.0,"larceny":42.0,"motor_theft":5.2,"soc_sec":14.6,"nuclear":13.4,"coal":62.1,"tr_deaths":10.5,"tr_deaths_no_alc":1.2,"unempl":5.7},{"state":"Mississippi","abbr":"MS","fips":28,"pop2010":2967297,"pop2000":2844658,"homeownership":70.8,"multiunit":13.4,"income":19977,"med_income":37881,"poverty":21.2,"fed_spend":11.1565134869,"land_area":46923.27,"smoke":23.7,"murder":7.3,"robbery":82.3,"agg_assault":5.0,"larceny":70.2,"motor_theft":8.6,"soc_sec":18.4,"nuclear":7.5,"coal":36.9,"tr_deaths":31.4,"tr_deaths_no_alc":2.0,"unempl":9.5},{"state":"Missouri","abbr":"MO","fips":29,"pop2010":5988927,"pop2000":5595211,"homeownership":70.0,"multiunit":19.6,"income":24724,"med_income":46262,"poverty":14.0,"fed_spend":11.2495298407,"land_area":68741.52,"smoke":23.4,"murder":6.9,"robbery":124.1,"agg_assault":6.1,"larceny":45.9,"motor_theft":7.4,"soc_sec":17.5,"nuclear":5.8,"coal":85.3,"tr_deaths":21.0,"tr_deaths_no_alc":1.0,"unempl":7.4},{"state":"Montana","abbr":"MT","fips":30,"pop2010":989415,"pop2000":902195,"homeownership":69.0,"multiunit":16.3,"income":23836,"med_income":43872,"poverty":14.5,"fed_spend":10.4637932516,"land_area":145545.8,"smoke":19.2,"murder":null,"robbery":null,"agg_assault":null,"larceny":null,"motor_theft":null,"soc_sec":16.8,"nuclear":0.0,"coal":63.8,"tr_deaths":25.4,"tr_deaths_no_alc":5.1,"unempl":6.2},{"state":"Nebraska","abbr":"NE","fips":31,"pop2010":1826341,"pop2000":1711263,"homeownership":68.6,"multiunit":19.3,"income":25229,"med_income":49342,"poverty":11.8,"fed_spend":9.193895335,"land_area":76824.17,"smoke":21.3,"murder":2.5,"robbery":59.1,"agg_assault":10.5,"larceny":141.0,"motor_theft":17.3,"soc_sec":15.9,"nuclear":17.6,"coal":66.2,"tr_deaths":15.1,"tr_deaths_no_alc":3.7,"unempl":4.0},{"state":"Nevada","abbr":"NV","fips":32,"pop2010":2700551,"pop2000":1998257,"homeownership":60.1,"multiunit":29.4,"income":27589,"med_income":55726,"poverty":11.9,"fed_spend":7.3665385323,"land_area":109781.18,"smoke":23.1,"murder":8.5,"robbery":194.7,"agg_assault":13.4,"larceny":79.8,"motor_theft":41.3,"soc_sec":12.6,"nuclear":0.0,"coal":45.7,"tr_deaths":15.8,"tr_deaths_no_alc":2.3,"unempl":12.3},{"state":"New Hampshire","abbr":"NH","fips":33,"pop2010":1316470,"pop2000":1235786,"homeownership":72.6,"multiunit":25.7,"income":31422,"med_income":63277,"poverty":7.8,"fed_spend":8.9454791982,"land_area":8952.65,"smoke":20.5,"murder":1.4,"robbery":27.4,"agg_assault":5.5,"larceny":104.6,"motor_theft":7.8,"soc_sec":16.6,"nuclear":28.2,"coal":17.2,"tr_deaths":12.6,"tr_deaths_no_alc":4.9,"unempl":5.2},{"state":"New Jersey","abbr":"NJ","fips":34,"pop2010":8791894,"pop2000":8414350,"homeownership":66.9,"multiunit":36.0,"income":34858,"med_income":69811,"poverty":9.1,"fed_spend":9.0529341004,"land_area":7354.22,"smoke":18.1,"murder":4.8,"robbery":151.6,"agg_assault":2.1,"larceny":17.8,"motor_theft":3.6,"soc_sec":15.6,"nuclear":22.7,"coal":19.2,"tr_deaths":8.5,"tr_deaths_no_alc":0.7,"unempl":9.0},{"state":"New Mexico","abbr":"NM","fips":35,"pop2010":2059179,"pop2000":1819046,"homeownership":69.6,"multiunit":15.1,"income":22966,"med_income":43820,"poverty":18.4,"fed_spend":13.3406634392,"land_area":121298.15,"smoke":21.5,"murder":7.4,"robbery":98.7,"agg_assault":26.3,"larceny":128.2,"motor_theft":20.1,"soc_sec":14.8,"nuclear":0.0,"coal":85.2,"tr_deaths":23.7,"tr_deaths_no_alc":3.0,"unempl":7.2},{"state":"New York","abbr":"NY","fips":36,"pop2010":19378102,"pop2000":18976457,"homeownership":55.2,"multiunit":50.6,"income":30948,"med_income":55603,"poverty":14.2,"fed_spend":10.0635567405,"land_area":47126.4,"smoke":20.5,"murder":4.5,"robbery":182.7,"agg_assault":1.2,"larceny":8.1,"motor_theft":1.0,"soc_sec":15.7,"nuclear":13.2,"coal":14.0,"tr_deaths":7.4,"tr_deaths_no_alc":0.3,"unempl":8.5},{"state":"North Carolina","abbr":"NC","fips":37,"pop2010":9535483,"pop2000":8049313,"homeownership":68.1,"multiunit":16.9,"income":24745,"med_income":45570,"poverty":15.5,"fed_spend":9.0025744894,"land_area":48617.91,"smoke":22.7,"murder":6.7,"robbery":145.5,"agg_assault":3.0,"larceny":26.7,"motor_theft":3.4,"soc_sec":15.4,"nuclear":18.2,"coal":60.5,"tr_deaths":16.1,"tr_deaths_no_alc":0.7,"unempl":9.9},{"state":"North Dakota","abbr":"ND","fips":38,"pop2010":672591,"pop2000":642200,"homeownership":66.6,"multiunit":25.9,"income":25803,"med_income":46781,"poverty":12.3,"fed_spend":13.2954038933,"land_area":69000.8,"smoke":20.0,"murder":1.1,"robbery":7.4,"agg_assault":9.7,"larceny":223.1,"motor_theft":24.7,"soc_sec":17.1,"nuclear":0.0,"coal":94.8,"tr_deaths":18.3,"tr_deaths_no_alc":7.8,"unempl":3.1},{"state":"Ohio","abbr":"OH","fips":39,"pop2010":11536504,"pop2000":11353140,"homeownership":69.2,"multiunit":23.0,"income":25113,"med_income":47358,"poverty":14.2,"fed_spend":9.1165757841,"land_area":40860.69,"smoke":22.3,"murder":5.1,"robbery":163.1,"agg_assault":1.2,"larceny":21.1,"motor_theft":3.1,"soc_sec":16.9,"nuclear":6.2,"coal":87.2,"tr_deaths":11.5,"tr_deaths_no_alc":0.5,"unempl":7.6},{"state":"Oklahoma","abbr":"OK","fips":40,"pop2010":3751351,"pop2000":3450654,"homeownership":68.2,"multiunit":15.3,"income":23094,"med_income":42979,"poverty":16.2,"fed_spend":10.1941964375,"land_area":68594.92,"smoke":25.1,"murder":5.3,"robbery":91.0,"agg_assault":9.9,"larceny":70.5,"motor_theft":10.4,"soc_sec":16.6,"nuclear":0.0,"coal":53.0,"tr_deaths":21.4,"tr_deaths_no_alc":1.7,"unempl":6.0},{"state":"Oregon","abbr":"OR","fips":41,"pop2010":3831074,"pop2000":3421399,"homeownership":63.8,"multiunit":23.3,"income":26171,"med_income":49260,"poverty":14.0,"fed_spend":8.7703114061,"land_area":95988.01,"smoke":18.5,"murder":2.2,"robbery":68.1,"agg_assault":4.7,"larceny":81.2,"motor_theft":13.8,"soc_sec":15.9,"nuclear":0.0,"coal":7.0,"tr_deaths":12.7,"tr_deaths_no_alc":1.7,"unempl":8.8},{"state":"Pennsylvania","abbr":"PA","fips":42,"pop2010":12702379,"pop2000":12281054,"homeownership":71.0,"multiunit":20.7,"income":27049,"med_income":50398,"poverty":12.4,"fed_spend":11.0121622887,"land_area":44742.7,"smoke":23.7,"murder":6.1,"robbery":154.6,"agg_assault":1.9,"larceny":13.6,"motor_theft":1.9,"soc_sec":18.9,"nuclear":20.5,"coal":55.5,"tr_deaths":12.7,"tr_deaths_no_alc":0.5,"unempl":7.6},{"state":"Rhode Island","abbr":"RI","fips":44,"pop2010":1052567,"pop2000":1048319,"homeownership":62.5,"multiunit":40.5,"income":28707,"med_income":54902,"poverty":12.2,"fed_spend":10.8698116129,"land_area":1033.81,"smoke":19.8,"murder":3.2,"robbery":72.1,"agg_assault":13.9,"larceny":172.5,"motor_theft":38.8,"soc_sec":18.2,"nuclear":0.0,"coal":0.0,"tr_deaths":8.3,"tr_deaths_no_alc":4.8,"unempl":11.0},{"state":"South Carolina","abbr":"SC","fips":45,"pop2010":4625364,"pop2000":4012012,"homeownership":69.9,"multiunit":17.4,"income":23443,"med_income":43939,"poverty":16.4,"fed_spend":10.4492273473,"land_area":30060.7,"smoke":22.6,"murder":7.4,"robbery":132.1,"agg_assault":12.5,"larceny":63.9,"motor_theft":8.3,"soc_sec":16.2,"nuclear":28.7,"coal":38.7,"tr_deaths":23.6,"tr_deaths_no_alc":1.2,"unempl":9.1},{"state":"South Dakota","abbr":"SD","fips":46,"pop2010":814180,"pop2000":754844,"homeownership":68.9,"multiunit":18.5,"income":24110,"med_income":46369,"poverty":13.7,"fed_spend":11.8447112432,"land_area":75811.0,"smoke":19.8,"murder":2.3,"robbery":18.6,"agg_assault":13.3,"larceny":165.0,"motor_theft":13.3,"soc_sec":17.2,"nuclear":0.0,"coal":46.0,"tr_deaths":22.8,"tr_deaths_no_alc":7.0,"unempl":4.3},{"state":"Tennessee","abbr":"TN","fips":47,"pop2010":6346105,"pop2000":5689283,"homeownership":69.6,"multiunit":18.1,"income":23722,"med_income":43314,"poverty":16.5,"fed_spend":10.3252792067,"land_area":41234.9,"smoke":26.8,"murder":7.2,"robbery":167.3,"agg_assault":8.5,"larceny":44.6,"motor_theft":6.6,"soc_sec":16.9,"nuclear":16.4,"coal":61.0,"tr_deaths":20.0,"tr_deaths_no_alc":1.0,"unempl":8.0},{"state":"Texas","abbr":"TX","fips":48,"pop2010":25145561,"pop2000":20851820,"homeownership":64.8,"multiunit":24.1,"income":24870,"med_income":49646,"poverty":16.8,"fed_spend":8.6050754246,"land_area":261231.71,"smoke":20.0,"murder":6.2,"robbery":156.6,"agg_assault":1.3,"larceny":11.8,"motor_theft":1.6,"soc_sec":11.4,"nuclear":4.8,"coal":37.4,"tr_deaths":13.9,"tr_deaths_no_alc":0.2,"unempl":7.1},{"state":"Utah","abbr":"UT","fips":49,"pop2010":2763885,"pop2000":2233169,"homeownership":71.2,"multiunit":21.4,"income":23139,"med_income":56330,"poverty":10.8,"fed_spend":8.0824082768,"land_area":82169.62,"smoke":11.5,"murder":2.3,"robbery":44.3,"agg_assault":5.2,"larceny":105.6,"motor_theft":12.4,"soc_sec":9.5,"nuclear":0.0,"coal":94.2,"tr_deaths":10.2,"tr_deaths_no_alc":3.1,"unempl":5.7},{"state":"Vermont","abbr":"VT","fips":50,"pop2010":625741,"pop2000":608827,"homeownership":71.4,"multiunit":23.2,"income":27478,"med_income":51841,"poverty":11.1,"fed_spend":10.8224121482,"land_area":9216.66,"smoke":19.3,"murder":1.3,"robbery":11.7,"agg_assault":13.3,"larceny":269.5,"motor_theft":16.4,"soc_sec":17.6,"nuclear":50.5,"coal":0.0,"tr_deaths":11.7,"tr_deaths_no_alc":9.6,"unempl":4.9},{"state":"Virginia","abbr":"VA","fips":51,"pop2010":8001024,"pop2000":7078515,"homeownership":68.9,"multiunit":21.4,"income":32145,"med_income":61406,"poverty":10.3,"fed_spend":15.9727087433,"land_area":39490.09,"smoke":20.6,"murder":6.1,"robbery":99.2,"agg_assault":1.9,"larceny":25.4,"motor_theft":2.6,"soc_sec":13.9,"nuclear":15.2,"coal":44.9,"tr_deaths":11.8,"tr_deaths_no_alc":0.8,"unempl":5.7},{"state":"Washington","abbr":"WA","fips":53,"pop2010":6724540,"pop2000":5894121,"homeownership":64.8,"multiunit":25.9,"income":29733,"med_income":57244,"poverty":12.1,"fed_spend":10.2581404825,"land_area":66455.52,"smoke":17.6,"murder":3.3,"robbery":92.1,"agg_assault":3.1,"larceny":46.8,"motor_theft":11.7,"soc_sec":13.6,"nuclear":4.1,"coal":10.3,"tr_deaths":9.6,"tr_deaths_no_alc":0.8,"unempl":8.2},{"state":"West Virginia","abbr":"WV","fips":54,"pop2010":1852994,"pop2000":1808344,"homeownership":74.6,"multiunit":12.1,"income":21232,"med_income":38380,"poverty":17.4,"fed_spend":11.044192264,"land_area":24038.21,"smoke":26.6,"murder":4.4,"robbery":44.6,"agg_assault":11.1,"larceny":96.8,"motor_theft":11.3,"soc_sec":22.0,"nuclear":0.0,"coal":97.6,"tr_deaths":20.2,"tr_deaths_no_alc":3.6,"unempl":7.2},{"state":"Wisconsin","abbr":"WI","fips":55,"pop2010":5686986,"pop2000":5363675,"homeownership":69.5,"multiunit":25.5,"income":26624,"med_income":51598,"poverty":11.6,"fed_spend":9.2416269356,"land_area":54157.8,"smoke":20.8,"murder":3.5,"robbery":82.2,"agg_assault":2.4,"larceny":35.0,"motor_theft":4.0,"soc_sec":16.5,"nuclear":9.8,"coal":67.4,"tr_deaths":14.3,"tr_deaths_no_alc":1.0,"unempl":6.9},{"state":"Wyoming","abbr":"WY","fips":56,"pop2010":563626,"pop2000":493782,"homeownership":70.2,"multiunit":15.8,"income":27860,"med_income":53802,"poverty":9.8,"fed_spend":11.5430924052,"land_area":97093.14,"smoke":21.3,"murder":2.7,"robbery":15.3,"agg_assault":33.4,"larceny":449.6,"motor_theft":25.7,"soc_sec":14.7,"nuclear":0.0,"coal":95.1,"tr_deaths":30.2,"tr_deaths_no_alc":11.0,"unempl":5.4}]